[{"name":"David Rubert","login":"tombatossals","location":"Castelló de la Plana","language":"JavaScript","gravatar":"https://avatars1.githubusercontent.com/u/124169?v=3&s=64","followers":92,"user_stars":"220","stars":197,"organizations":[],"contributions":762,"contributionsStreak":11,"contributionsCurrentStreak":0},{"name":"Nacho Miralles","login":"nachomiralles","location":"Castellón, Spain.","language":"HTML","gravatar":"https://avatars1.githubusercontent.com/u/4831513?v=3&s=64","followers":2,"user_stars":"0","stars":0,"organizations":[],"contributions":135,"contributionsStreak":3,"contributionsCurrentStreak":0},{"name":"Tadeo Julián Segarra","login":"tadeoj","location":"Castellón de la plana","language":"Java","gravatar":"https://avatars2.githubusercontent.com/u/5433570?v=3&s=64","followers":0,"user_stars":"0","stars":0,"organizations":[],"contributions":115,"contributionsStreak":6,"contributionsCurrentStreak":0},{"name":"Óscar Belmonte Fernández","login":"oscarbelmon","location":"Castellón de la Plana","language":"Java","gravatar":"https://avatars3.githubusercontent.com/u/4066452?v=3&s=64","followers":1,"user_stars":"10","stars":0,"organizations":[],"contributions":93,"contributionsStreak":5,"contributionsCurrentStreak":0},{"name":"Miguel Campins","login":"s1vh","location":"Castellón de la Plana","language":"HTML and ActionScript","gravatar":"https://avatars2.githubusercontent.com/u/9099118?v=3&s=64","followers":2,"user_stars":"0","stars":0,"organizations":[],"contributions":62,"contributionsStreak":4,"contributionsCurrentStreak":0},{"name":"Juan Carlos García","login":"jcgarsan","location":"Castellón (Spain)","language":"C++","gravatar":"https://avatars0.githubusercontent.com/u/5547857?v=3&s=64","followers":1,"user_stars":"0","stars":0,"organizations":[],"contributions":48,"contributionsStreak":4,"contributionsCurrentStreak":0},{"name":"Andersson Gabriel","login":"ander7agar","location":"Castellón, España","language":"Java and Shell","gravatar":"https://avatars1.githubusercontent.com/u/6875232?v=3&s=64","followers":2,"user_stars":"0","stars":0,"organizations":[],"contributions":37,"contributionsStreak":4,"contributionsCurrentStreak":0},{"name":"José Luis Aracil Gómez del Campo","login":"jaracil","location":"Castellón, Spain","language":"Go","gravatar":"https://avatars3.githubusercontent.com/u/6370372?v=3&s=64","followers":7,"user_stars":"31","stars":26,"organizations":[],"contributions":35,"contributionsStreak":5,"contributionsCurrentStreak":0},{"name":"Marcos Mariscal","login":"MMariscal","location":"Carretera Viver - Puerto de Burriana, Km 61,4, s/n Apdo 451, 12540 Villareal, Castellón","language":"JavaScript","gravatar":"https://avatars1.githubusercontent.com/u/7589691?v=3&s=64","followers":0,"user_stars":"1","stars":0,"organizations":[],"contributions":34,"contributionsStreak":4,"contributionsCurrentStreak":0},{"name":"Lluís Tomàs Falcó Cascon","login":"lluistfc","location":"Castelló de la Plana","language":"PHP","gravatar":"https://avatars2.githubusercontent.com/u/8427953?v=3&s=64","followers":0,"user_stars":"0","stars":0,"organizations":[],"contributions":19,"contributionsStreak":2,"contributionsCurrentStreak":2},{"name":"Christian Bongardt","login":"chrbongardt","location":"Castellón","language":"Objective-C and Ruby","gravatar":"https://avatars0.githubusercontent.com/u/2834466?v=3&s=64","followers":4,"user_stars":"7","stars":1,"organizations":[],"contributions":13,"contributionsStreak":1,"contributionsCurrentStreak":0},{"name":"Jacobo Tarragón","login":"jminuscula","location":"Benicasim, Spain","language":"JavaScript","gravatar":"https://avatars3.githubusercontent.com/u/209764?v=3&s=64","followers":0,"user_stars":"37","stars":0,"organizations":[],"contributions":13,"contributionsStreak":2,"contributionsCurrentStreak":0},{"name":"Lucas Doe Santos","login":"lucasDoe","location":"Castellón","language":"Java","gravatar":"https://avatars1.githubusercontent.com/u/651637?v=3&s=64","followers":1,"user_stars":"2","stars":1,"organizations":[],"contributions":12,"contributionsStreak":2,"contributionsCurrentStreak":0},{"name":"David Rubert","login":"vrubert","location":"Castellón de la Plana (Spain)","language":"","gravatar":"https://avatars3.githubusercontent.com/u/3628879?v=3&s=64","followers":0,"user_stars":"6","stars":0,"organizations":[],"contributions":8,"contributionsStreak":1,"contributionsCurrentStreak":0},{"name":"SackCastellon","login":"SackCastellon","location":"Castellón, Comunidad Valenciana, Spain","language":"Java","gravatar":"https://avatars0.githubusercontent.com/u/5330355?v=3&s=64","followers":1,"user_stars":"2","stars":3,"organizations":[],"contributions":3,"contributionsStreak":1,"contributionsCurrentStreak":0},{"name":"Ramón García","login":"rmngrc","location":"Castellón (Spain)","language":"JavaScript","gravatar":"https://avatars3.githubusercontent.com/u/1866422?v=3&s=64","followers":3,"user_stars":"4","stars":0,"organizations":[],"contributions":2,"contributionsStreak":1,"contributionsCurrentStreak":0},{"name":"Toni Peñalver","login":"penalvea","location":"Castellón (Spain)","language":"C++","gravatar":"https://avatars0.githubusercontent.com/u/4102114?v=3&s=64","followers":2,"user_stars":"0","stars":0,"organizations":[],"contributions":2,"contributionsStreak":1,"contributionsCurrentStreak":0},{"name":"Aitor Quinza","login":"aitorquinza","location":"Castellón","language":"Makefile","gravatar":"https://avatars0.githubusercontent.com/u/2361502?v=3&s=64","followers":2,"user_stars":"1","stars":0,"organizations":[],"contributions":1,"contributionsStreak":1,"contributionsCurrentStreak":0},{"name":"Carles Bellver Torlà","login":"carlesbellver","location":"Castelló de la Plana","language":"CSS","gravatar":"https://avatars0.githubusercontent.com/u/129889?v=3&s=64","followers":0,"user_stars":"33","stars":1,"organizations":[],"contributions":1,"contributionsStreak":1,"contributionsCurrentStreak":0},{"name":"Pablo Rincón García","login":"CaptainAubergine","location":"Castellón de la Plana","language":"C#","gravatar":"https://avatars1.githubusercontent.com/u/7114094?v=3&s=64","followers":1,"user_stars":"0","stars":0,"organizations":[],"contributions":1,"contributionsStreak":1,"contributionsCurrentStreak":0},{"name":"Óscar Gómez","login":"OscardR","location":"Castellón de la Plana","language":"Java","gravatar":"https://avatars3.githubusercontent.com/u/1676200?v=3&s=64","followers":4,"user_stars":"17","stars":0,"organizations":[],"contributions":1,"contributionsStreak":1,"contributionsCurrentStreak":0}]