[{"name":"David Rubert","login":"tombatossals","location":"Castelló de la Plana","join_date":"Sep 7, 2009","language":"JavaScript","gravatar":"https://avatars1.githubusercontent.com/u/124169?v=3&s=64","followers":99,"user_stars":"237","stars":228,"organizations":[],"contributions":598,"contributionsStreak":10,"contributionsCurrentStreak":0},{"name":"Adrián Castelló","login":"adcastel","location":"Castellón de la Plana","join_date":"Oct 2, 2015","language":"Makefile","gravatar":"https://avatars3.githubusercontent.com/u/14941182?v=3&s=64","followers":0,"user_stars":"0","stars":0,"organizations":[],"contributions":294,"contributionsStreak":5,"contributionsCurrentStreak":0},{"name":"Javier Perez","login":"perezsolerj","location":"Castellon","join_date":"Apr 9, 2013","language":"C++","gravatar":"https://avatars2.githubusercontent.com/u/4101745?v=3&s=64","followers":5,"user_stars":"1","stars":0,"organizations":[],"contributions":180,"contributionsStreak":3,"contributionsCurrentStreak":0},{"name":"Óscar Belmonte Fernández","login":"oscarbelmon","location":"Castellón de la Plana","join_date":"Apr 5, 2013","language":"Java","gravatar":"https://avatars3.githubusercontent.com/u/4066452?v=3&s=64","followers":5,"user_stars":"10","stars":0,"organizations":[],"contributions":154,"contributionsStreak":5,"contributionsCurrentStreak":0},{"name":"Nacho Miralles","login":"nachomiralles","location":"Castellón, Spain.","join_date":"Jun 26, 2013","language":"HTML","gravatar":"https://avatars1.githubusercontent.com/u/4831513?v=3&s=64","followers":2,"user_stars":"0","stars":0,"organizations":[],"contributions":139,"contributionsStreak":3,"contributionsCurrentStreak":0},{"name":"Miguel Campins","login":"s1vh","location":"Castellón de la Plana","join_date":"Oct 9, 2014","language":"C#","gravatar":"https://avatars2.githubusercontent.com/u/9099118?v=3&s=64","followers":2,"user_stars":"2","stars":0,"organizations":[],"contributions":131,"contributionsStreak":4,"contributionsCurrentStreak":0},{"name":"Tadeo Julián Segarra","login":"tadeoj","location":"Castellón de la plana","join_date":"Sep 11, 2013","language":"Java","gravatar":"https://avatars2.githubusercontent.com/u/5433570?v=3&s=64","followers":0,"user_stars":"0","stars":0,"organizations":[],"contributions":117,"contributionsStreak":6,"contributionsCurrentStreak":0},{"name":"Piotr Usewicz","login":"pusewicz","location":"Benicarló, Spain","join_date":"Feb 26, 2008","language":"Ruby","gravatar":"https://avatars1.githubusercontent.com/u/940?v=3&s=64","followers":27,"user_stars":"625","stars":263,"organizations":[],"contributions":87,"contributionsStreak":2,"contributionsCurrentStreak":0},{"name":"Daniel Pecos Martinez","login":"dpecos","location":"Castellón","join_date":"Jan 26, 2011","language":"JavaScript","gravatar":"https://avatars3.githubusercontent.com/u/584298?v=3&s=64","followers":12,"user_stars":"47","stars":8,"organizations":[],"contributions":77,"contributionsStreak":3,"contributionsCurrentStreak":0},{"name":"Luca Mearelli","login":"luca","location":"Citta' di Castello, Italy","join_date":"Apr 3, 2008","language":"JavaScript","gravatar":"https://avatars0.githubusercontent.com/u/4583?v=3&s=64","followers":12,"user_stars":"137","stars":63,"organizations":[],"contributions":58,"contributionsStreak":3,"contributionsCurrentStreak":0},{"name":"Juan Carlos García","login":"jcgarsan","location":"Castellón (Spain)","join_date":"Sep 26, 2013","language":"C++","gravatar":"https://avatars0.githubusercontent.com/u/5547857?v=3&s=64","followers":2,"user_stars":"0","stars":0,"organizations":[],"contributions":52,"contributionsStreak":2,"contributionsCurrentStreak":0},{"name":"Albert Jiménez","login":"albertjimenez","location":"Castellón","join_date":"May 21, 2015","language":"Java","gravatar":"https://avatars0.githubusercontent.com/u/12547680?v=3&s=64","followers":2,"user_stars":"6","stars":0,"organizations":[],"contributions":49,"contributionsStreak":5,"contributionsCurrentStreak":0},{"name":"Andersson Gabriel","login":"ander7agar","location":"Castellón, España","join_date":"Mar 6, 2014","language":"Java and Shell","gravatar":"https://avatars1.githubusercontent.com/u/6875232?v=3&s=64","followers":3,"user_stars":"0","stars":1,"organizations":[],"contributions":47,"contributionsStreak":4,"contributionsCurrentStreak":0},{"name":"Manuel Palomo","login":"ManuelPalomo","location":"Castellon,Spain","join_date":"Oct 5, 2011","language":"Java","gravatar":"https://avatars1.githubusercontent.com/u/1106106?v=3&s=64","followers":0,"user_stars":"3","stars":0,"organizations":[],"contributions":46,"contributionsStreak":5,"contributionsCurrentStreak":0},{"name":"","login":"carsolcas","location":"Castellon (Spain)","join_date":"Aug 12, 2013","language":"JavaScript","gravatar":"https://avatars3.githubusercontent.com/u/5211471?v=3&s=64","followers":1,"user_stars":"0","stars":1,"organizations":[],"contributions":40,"contributionsStreak":3,"contributionsCurrentStreak":0},{"name":"José Luis Aracil Gómez del Campo","login":"jaracil","location":"Castellón, Spain","join_date":"Jan 10, 2014","language":"Go","gravatar":"https://avatars3.githubusercontent.com/u/6370372?v=3&s=64","followers":7,"user_stars":"34","stars":26,"organizations":[],"contributions":35,"contributionsStreak":5,"contributionsCurrentStreak":0},{"name":"Sergio Formiggini","login":"sirjoblack","location":"Castello di Cisterna (NA) Italy","join_date":"Dec 25, 2014","language":"C++","gravatar":"https://avatars3.githubusercontent.com/u/10294925?v=3&s=64","followers":0,"user_stars":"1","stars":2,"organizations":[],"contributions":23,"contributionsStreak":3,"contributionsCurrentStreak":0},{"name":"Bulent Ozel","login":"bulentozel","location":"Castellon De La Plana, Spain","join_date":"Oct 19, 2012","language":"R","gravatar":"https://avatars1.githubusercontent.com/u/2594197?v=3&s=64","followers":2,"user_stars":"0","stars":4,"organizations":[],"contributions":17,"contributionsStreak":2,"contributionsCurrentStreak":0},{"name":"David Rubert","login":"vrubert","location":"Castellón de la Plana (Spain)","join_date":"Feb 18, 2013","language":"","gravatar":"https://avatars3.githubusercontent.com/u/3628879?v=3&s=64","followers":0,"user_stars":"13","stars":0,"organizations":[],"contributions":15,"contributionsStreak":3,"contributionsCurrentStreak":0},{"name":"Salva Savall","login":"SalvaSavall","location":"Castellon (Spain)","join_date":"Mar 20, 2014","language":"Java","gravatar":"https://avatars3.githubusercontent.com/u/7012533?v=3&s=64","followers":0,"user_stars":"0","stars":0,"organizations":[],"contributions":14,"contributionsStreak":4,"contributionsCurrentStreak":0},{"name":"Lucas Doe Santos","login":"lucasDoe","location":"Castellón","join_date":"Mar 4, 2011","language":"Assembly","gravatar":"https://avatars1.githubusercontent.com/u/651637?v=3&s=64","followers":1,"user_stars":"2","stars":1,"organizations":[],"contributions":12,"contributionsStreak":2,"contributionsCurrentStreak":0},{"name":"","login":"agallen","location":"Castellon","join_date":"Dec 21, 2015","language":"Batchfile and C#","gravatar":"https://avatars0.githubusercontent.com/u/16383843?v=3&s=64","followers":0,"user_stars":"0","stars":0,"organizations":[],"contributions":10,"contributionsStreak":2,"contributionsCurrentStreak":0},{"name":"Javier Iranzo Rebenaque","login":"javirareb","location":"Castellón de la Plana, España","join_date":"Feb 23, 2016","language":"Java and Kotlin","gravatar":"https://avatars1.githubusercontent.com/u/17440402?v=3&s=64","followers":0,"user_stars":"0","stars":0,"organizations":[],"contributions":4,"contributionsStreak":2,"contributionsCurrentStreak":0},{"name":"Carlos Rubert","login":"Cescuder","location":"Castellon(Spain)","join_date":"Jan 15, 2014","language":"C++","gravatar":"https://avatars0.githubusercontent.com/u/6408620?v=3&s=64","followers":1,"user_stars":"1","stars":0,"organizations":[],"contributions":4,"contributionsStreak":1,"contributionsCurrentStreak":0},{"name":"Toni Peñalver","login":"penalvea","location":"Castellón (Spain)","join_date":"Apr 9, 2013","language":"C++","gravatar":"https://avatars0.githubusercontent.com/u/4102114?v=3&s=64","followers":2,"user_stars":"0","stars":0,"organizations":[],"contributions":3,"contributionsStreak":1,"contributionsCurrentStreak":0},{"name":"Juanjo Bru","login":"Juanjobru","location":"Castellon, Spain","join_date":"Feb 1, 2016","language":"","gravatar":"https://avatars1.githubusercontent.com/u/17012514?v=3&s=64","followers":0,"user_stars":"0","stars":0,"organizations":[],"contributions":3,"contributionsStreak":1,"contributionsCurrentStreak":0},{"name":"user--","login":"user-faghloumi","location":"benicarlo","join_date":"Apr 4, 2013","language":"","gravatar":"https://avatars2.githubusercontent.com/u/4062367?v=3&s=64","followers":0,"user_stars":"2","stars":1,"organizations":[],"contributions":3,"contributionsStreak":1,"contributionsCurrentStreak":0},{"name":"SackCastellon","login":"SackCastellon","location":"Castellón, Comunidad Valenciana, Spain","join_date":"Aug 28, 2013","language":"Java","gravatar":"https://avatars0.githubusercontent.com/u/5330355?v=3&s=64","followers":1,"user_stars":"2","stars":3,"organizations":[],"contributions":2,"contributionsStreak":1,"contributionsCurrentStreak":0},{"name":"Pablo Mateu","login":"PabloMateu","location":"Castelló","join_date":"Jan 31, 2016","language":"Java","gravatar":"https://avatars3.githubusercontent.com/u/16989551?v=3&s=64","followers":0,"user_stars":"0","stars":0,"organizations":[],"contributions":2,"contributionsStreak":1,"contributionsCurrentStreak":0},{"name":"","login":"eVolaXx","location":"Almazora, Castellon","join_date":"Mar 2, 2014","language":"Java","gravatar":"https://avatars3.githubusercontent.com/u/6832181?v=3&s=64","followers":1,"user_stars":"6","stars":0,"organizations":[],"contributions":1,"contributionsStreak":1,"contributionsCurrentStreak":0},{"name":"Pablo Rincón García","login":"CaptainAubergine","location":"Castellón de la Plana","join_date":"Mar 31, 2014","language":"C#","gravatar":"https://avatars1.githubusercontent.com/u/7114094?v=3&s=64","followers":1,"user_stars":"0","stars":0,"organizations":[],"contributions":1,"contributionsStreak":1,"contributionsCurrentStreak":0},{"name":"Carles Bellver Torlà","login":"carlesbellver","location":"Castelló de la Plana","join_date":"Sep 22, 2009","language":"CSS","gravatar":"https://avatars0.githubusercontent.com/u/129889?v=3&s=64","followers":1,"user_stars":"36","stars":1,"organizations":[],"contributions":1,"contributionsStreak":1,"contributionsCurrentStreak":0},{"name":"Pedro Cid","login":"pedrocid","location":"Castellón, Spain","join_date":"Oct 9, 2012","language":"Swift","gravatar":"https://avatars3.githubusercontent.com/u/2520999?v=3&s=64","followers":1,"user_stars":"10","stars":0,"organizations":[],"contributions":1,"contributionsStreak":1,"contributionsCurrentStreak":0},{"name":"Cristian Castillo","login":"castillo2310","location":"Castellón de la Plana, Spain","join_date":"Oct 28, 2013","language":"","gravatar":"https://avatars3.githubusercontent.com/u/5794177?v=3&s=64","followers":0,"user_stars":"0","stars":0,"organizations":[],"contributions":1,"contributionsStreak":1,"contributionsCurrentStreak":0},{"name":"Aitor Quinza","login":"aitorquinza","location":"Castellón","join_date":"Sep 17, 2012","language":"JavaScript","gravatar":"https://avatars0.githubusercontent.com/u/2361502?v=3&s=64","followers":4,"user_stars":"2","stars":0,"organizations":[],"contributions":1,"contributionsStreak":1,"contributionsCurrentStreak":0},{"name":"Kim Schulte","login":"ks10007","location":"Castellón","join_date":"Nov 29, 2015","language":"","gravatar":"https://avatars2.githubusercontent.com/u/16067420?v=3&s=64","followers":0,"user_stars":"0","stars":0,"organizations":[],"contributions":1,"contributionsStreak":1,"contributionsCurrentStreak":0},{"name":"Sergio Gragera","login":"sergiogragera","location":"Castellón","join_date":"Feb 12, 2011","language":"","gravatar":"https://avatars3.githubusercontent.com/u/614262?v=3&s=64","followers":0,"user_stars":"8","stars":0,"organizations":[],"contributions":1,"contributionsStreak":1,"contributionsCurrentStreak":0},{"name":"Óscar Gómez","login":"OscardR","location":"Castellón de la Plana","join_date":"Apr 24, 2012","language":"Java","gravatar":"https://avatars3.githubusercontent.com/u/1676200?v=3&s=64","followers":4,"user_stars":"17","stars":0,"organizations":[],"contributions":1,"contributionsStreak":1,"contributionsCurrentStreak":0},{"name":"Hector Martinez","login":"martineh","location":"CASTELLON","join_date":"Jan 15, 2013","language":"CSS","gravatar":"https://avatars1.githubusercontent.com/u/3277966?v=3&s=64","followers":1,"user_stars":"0","stars":0,"organizations":[],"contributions":1,"contributionsStreak":1,"contributionsCurrentStreak":0},{"name":"Marc","login":"marfeldesign","location":"Benicarló","join_date":"Oct 1, 2013","language":"JavaScript","gravatar":"https://avatars0.githubusercontent.com/u/5584924?v=3&s=64","followers":1,"user_stars":"0","stars":0,"organizations":[],"contributions":1,"contributionsStreak":1,"contributionsCurrentStreak":0}]