[{"name":"javi santana","login":"javisantana","location":"Madrid - Valladolid","language":"JavaScript","gravatar":"https://avatars1.githubusercontent.com/u/30147?v=3&s=64","followers":130,"stars":120,"organizations":["Vizzuality","modestmaps","CartoDB"],"contributions":1887,"contributionsStreak":11,"contributionsCurrentStreak":0},{"name":"Juan Ignacio Sánchez Lara","login":"juanignaciosl","location":"Valladolid","language":"JavaScript","gravatar":"https://avatars1.githubusercontent.com/u/932968?v=3&s=64","followers":17,"stars":15,"organizations":[],"contributions":1184,"contributionsStreak":13,"contributionsCurrentStreak":0},{"name":"Joaquín Ferrero","login":"joaquinferrero","location":"Valladolid, Spain","language":"Perl","gravatar":"https://avatars1.githubusercontent.com/u/250681?v=3&s=64","followers":3,"stars":1,"organizations":[],"contributions":1058,"contributionsStreak":8,"contributionsCurrentStreak":0},{"name":"Adrián Arroyo Calle","login":"AdrianArroyoCalle","location":"Valladolid, Spain","language":"JavaScript","gravatar":"https://avatars1.githubusercontent.com/u/3681517?v=3&s=64","followers":9,"stars":34,"organizations":[],"contributions":664,"contributionsStreak":9,"contributionsCurrentStreak":0},{"name":"Marcos García","login":"marcosgdf","location":"Valladolid, Spain","language":"PHP","gravatar":"https://avatars2.githubusercontent.com/u/168744?v=3&s=64","followers":11,"stars":10,"organizations":[],"contributions":612,"contributionsStreak":8,"contributionsCurrentStreak":0},{"name":"Alexander Nestorov","login":"alexandernst","location":"Valladolid, Spain","language":"JavaScript","gravatar":"https://avatars2.githubusercontent.com/u/89727?v=3&s=64","followers":29,"stars":28,"organizations":["amsn","backbone-paginator","BOFHers"],"contributions":475,"contributionsStreak":9,"contributionsCurrentStreak":0},{"name":"Pablo Lopez","login":"plopesc","location":"Valladolid, Spain","language":"PHP","gravatar":"https://avatars3.githubusercontent.com/u/161282?v=3&s=64","followers":6,"stars":6,"organizations":["idelab","Plug-Drupal"],"contributions":419,"contributionsStreak":5,"contributionsCurrentStreak":0},{"name":"Enrique Marcos","login":"enrmarc","location":"Valladolid, Spain","language":"JavaScript","gravatar":"https://avatars1.githubusercontent.com/u/408183?v=3&s=64","followers":7,"stars":54,"organizations":["coyotev"],"contributions":395,"contributionsStreak":9,"contributionsCurrentStreak":0},{"name":"Mario Izquierdo","login":"mariodebian","location":"Valladolid, Spain","language":"Shell","gravatar":"https://avatars0.githubusercontent.com/u/522472?v=3&s=64","followers":10,"stars":9,"organizations":["thinetic-systems","max-linux","MVScada"],"contributions":314,"contributionsStreak":6,"contributionsCurrentStreak":0},{"name":"José Pereda","login":"jperedadnr","location":"Valladolid, Spain","language":"Java","gravatar":"https://avatars3.githubusercontent.com/u/2043230?v=3&s=64","followers":22,"stars":14,"organizations":["JFXtras"],"contributions":299,"contributionsStreak":4,"contributionsCurrentStreak":0},{"name":"Javier Gonzalez","login":"javiergonzper","location":"Valladolid, Spain","language":"Objective-C","gravatar":"https://avatars2.githubusercontent.com/u/1815050?v=3&s=64","followers":6,"stars":0,"organizations":["owncloud"],"contributions":249,"contributionsStreak":5,"contributionsCurrentStreak":0},{"name":"Jorge Maroto","login":"patoroco","location":"Valladolid-Madrid, Spain","language":"Ruby","gravatar":"https://avatars0.githubusercontent.com/u/701909?v=3&s=64","followers":33,"stars":115,"organizations":["visualimpactmedia","TactilApp","ticketea","AFNBook"],"contributions":230,"contributionsStreak":4,"contributionsCurrentStreak":0},{"name":"Jesus A Hernandez de Rojas","login":"jhderojasUVa","location":"Valladolid","language":"CSS","gravatar":"https://avatars1.githubusercontent.com/u/2618598?v=3&s=64","followers":1,"stars":0,"organizations":["NewscoopTemplate"],"contributions":187,"contributionsStreak":9,"contributionsCurrentStreak":0},{"name":"Mario Milán Peña","login":"shkliciouz","location":"Valladolid","language":"JavaScript","gravatar":"https://avatars1.githubusercontent.com/u/6928516?v=3&s=64","followers":1,"stars":1,"organizations":[],"contributions":133,"contributionsStreak":5,"contributionsCurrentStreak":0},{"name":"Adrián de la Rosa","login":"ADLR-es","location":"Medina del Campo, Valladolid, Spain","language":"JavaScript","gravatar":"https://avatars1.githubusercontent.com/u/307945?v=3&s=64","followers":1,"stars":0,"organizations":[],"contributions":124,"contributionsStreak":4,"contributionsCurrentStreak":0},{"name":"Mario del Valle","login":"mariodelvalle","location":"Valladolid","language":"JavaScript and CSS","gravatar":"https://avatars1.githubusercontent.com/u/3064293?v=3&s=64","followers":10,"stars":63,"organizations":[],"contributions":112,"contributionsStreak":3,"contributionsCurrentStreak":0},{"name":"Mario de Frutos","login":"ethervoid","location":"Valladolid - Madrid","language":"Java","gravatar":"https://avatars2.githubusercontent.com/u/741240?v=3&s=64","followers":15,"stars":9,"organizations":[],"contributions":98,"contributionsStreak":3,"contributionsCurrentStreak":0},{"name":"Arkadoel","login":"arkadoel","location":"Valladolid, Spain","language":"Python","gravatar":"https://avatars3.githubusercontent.com/u/4712655?v=3&s=64","followers":2,"stars":7,"organizations":[],"contributions":91,"contributionsStreak":4,"contributionsCurrentStreak":0},{"name":"Dani Carrión","login":"danicarrion","location":"Valladolid, Spain","language":"Python","gravatar":"https://avatars2.githubusercontent.com/u/498023?v=3&s=64","followers":2,"stars":0,"organizations":[],"contributions":91,"contributionsStreak":5,"contributionsCurrentStreak":0},{"name":"Diego de las Heras","login":"ngosang","location":"Valladolid, Spain","language":"Shell","gravatar":"https://avatars3.githubusercontent.com/u/10577978?v=3&s=64","followers":0,"stars":2,"organizations":[],"contributions":91,"contributionsStreak":7,"contributionsCurrentStreak":0},{"name":"Guido García","login":"palmerabollo","location":"Valladolid, Spain","language":"JavaScript","gravatar":"https://avatars2.githubusercontent.com/u/673420?v=3&s=64","followers":15,"stars":53,"organizations":["telefonicaid","Telefonica","books4equality"],"contributions":88,"contributionsStreak":2,"contributionsCurrentStreak":0},{"name":"Javier Herrero","login":"JaviHerAr","location":"Valladolid, Spain","language":"Python and Pascal","gravatar":"https://avatars3.githubusercontent.com/u/1096471?v=3&s=400","followers":0,"stars":0,"organizations":[],"contributions":87,"contributionsStreak":2,"contributionsCurrentStreak":0},{"name":"Sergio Bertolín","login":"SergioBertolinSG","location":"Valladolid","language":"Python and Shell","gravatar":"https://avatars1.githubusercontent.com/u/9048796?v=3&s=64","followers":0,"stars":0,"organizations":[],"contributions":70,"contributionsStreak":5,"contributionsCurrentStreak":0},{"name":"Juan Pablo Villafañez","login":"jvillafanez","location":"Valladolid","language":"","gravatar":"https://avatars2.githubusercontent.com/u/1477829?v=3&s=64","followers":0,"stars":0,"organizations":[],"contributions":65,"contributionsStreak":5,"contributionsCurrentStreak":0},{"name":"linuxesdios","login":"linuxesdios","location":"valladolid","language":"Shell","gravatar":"https://avatars3.githubusercontent.com/u/2717922?v=3&s=64","followers":5,"stars":2,"organizations":[],"contributions":62,"contributionsStreak":3,"contributionsCurrentStreak":0},{"name":"Luis F. Nicolas-Alonso","login":"lnicalo","location":"Valladolid, Spain","language":"Python","gravatar":"https://avatars3.githubusercontent.com/u/9167447?v=3&s=64","followers":0,"stars":0,"organizations":[],"contributions":56,"contributionsStreak":4,"contributionsCurrentStreak":0},{"name":"Santi","login":"santirivera92","location":"Valladolid","language":"Java","gravatar":"https://avatars0.githubusercontent.com/u/1720747?v=3&s=64","followers":5,"stars":1,"organizations":[],"contributions":54,"contributionsStreak":4,"contributionsCurrentStreak":0},{"name":"Rafael Sillero","login":"Rsilnav","location":"Valladolid (Spain)","language":"Python","gravatar":"https://avatars1.githubusercontent.com/u/7466682?v=3&s=64","followers":0,"stars":0,"organizations":[],"contributions":49,"contributionsStreak":2,"contributionsCurrentStreak":0},{"name":"Puri García Romeralo","login":"purigarcia","location":"Valladolid, Spain","language":"","gravatar":"https://avatars2.githubusercontent.com/u/4538201?v=3&s=64","followers":0,"stars":0,"organizations":[],"contributions":37,"contributionsStreak":2,"contributionsCurrentStreak":0},{"name":"Ismael Taboada Rodero","login":"ismtabo","location":"Valladolid","language":"HTML","gravatar":"https://avatars2.githubusercontent.com/u/9568287?v=3&s=64","followers":4,"stars":0,"organizations":["guiuva"],"contributions":37,"contributionsStreak":6,"contributionsCurrentStreak":0},{"name":"Chema Peribáñez","login":"chemaper","location":"Valladolid, Spain.","language":"Shell","gravatar":"https://avatars0.githubusercontent.com/u/8962900?v=3&s=64","followers":0,"stars":0,"organizations":[],"contributions":28,"contributionsStreak":3,"contributionsCurrentStreak":0},{"name":"Antonio Ferreras","login":"ferreras","location":"Valladolid","language":"R","gravatar":"https://avatars2.githubusercontent.com/u/7223070?v=3&s=64","followers":0,"stars":0,"organizations":[],"contributions":25,"contributionsStreak":2,"contributionsCurrentStreak":0},{"name":"Néstor Díaz Valencia","login":"n3storm","location":"Valladolid, SPAIN","language":"Python","gravatar":"https://avatars2.githubusercontent.com/u/220748?v=3&s=64","followers":2,"stars":8,"organizations":[],"contributions":24,"contributionsStreak":2,"contributionsCurrentStreak":0},{"name":"Alejandro Martinez Andres","login":"Smokt","location":"Valladolid","language":"","gravatar":"https://avatars1.githubusercontent.com/u/11448715?v=3&s=64","followers":1,"stars":0,"organizations":[],"contributions":23,"contributionsStreak":1,"contributionsCurrentStreak":0},{"name":"Sergio Luis Para","login":"SergioLuis","location":"Laguna de Duero (Valladolid, SPAIN)","language":"Java","gravatar":"https://avatars1.githubusercontent.com/u/6057745?v=3&s=64","followers":4,"stars":18,"organizations":[],"contributions":22,"contributionsStreak":4,"contributionsCurrentStreak":0},{"name":"juliobm","login":"juliobm","location":"Valladolid","language":"Python","gravatar":"https://avatars2.githubusercontent.com/u/5206946?v=3&s=64","followers":2,"stars":0,"organizations":[],"contributions":21,"contributionsStreak":1,"contributionsCurrentStreak":0},{"name":"Jesus Macias Portela","login":"jmaciasportela","location":"Valladolid","language":"JavaScript","gravatar":"https://avatars1.githubusercontent.com/u/1454351?v=3&s=64","followers":5,"stars":7,"organizations":["thinetic-systems"],"contributions":20,"contributionsStreak":3,"contributionsCurrentStreak":0},{"name":"Alberto Amigo","login":"albamig","location":"Valladolid, Spain","language":"Assembly","gravatar":"https://avatars3.githubusercontent.com/u/6004070?v=3&s=64","followers":6,"stars":6,"organizations":[],"contributions":19,"contributionsStreak":2,"contributionsCurrentStreak":0},{"name":"José Antonio Yáñez Jiménez","login":"berikin","location":"Valladolid, Spain","language":"CSS","gravatar":"https://avatars3.githubusercontent.com/u/1564947?v=3&s=64","followers":4,"stars":5,"organizations":[],"contributions":18,"contributionsStreak":2,"contributionsCurrentStreak":0},{"name":"Miguel Jiménez","login":"miguelFLG13","location":"Valladolid","language":"Python","gravatar":"https://avatars0.githubusercontent.com/u/6031760?v=3&s=64","followers":0,"stars":0,"organizations":[],"contributions":16,"contributionsStreak":1,"contributionsCurrentStreak":0},{"name":"Javier Enrique Hoyos Torío","login":"javierht","location":"Valladolid - Spain","language":"","gravatar":"https://avatars0.githubusercontent.com/u/3501122?v=3&s=64","followers":2,"stars":0,"organizations":[],"contributions":15,"contributionsStreak":2,"contributionsCurrentStreak":0},{"name":"Eduardo Alonso","login":"ealogar","location":"Valladolid, Spain","language":"Python","gravatar":"https://avatars2.githubusercontent.com/u/2461944?v=3&s=64","followers":2,"stars":0,"organizations":["Telefonica"],"contributions":14,"contributionsStreak":1,"contributionsCurrentStreak":0},{"name":"Itziar","login":"itziarfm","location":"Valladolid, Spain","language":"","gravatar":"https://avatars0.githubusercontent.com/u/7221465?v=3&s=64","followers":0,"stars":0,"organizations":[],"contributions":12,"contributionsStreak":2,"contributionsCurrentStreak":0},{"name":"Ariel Hernán Curiale","login":"curiale","location":"Valladolid, Spain","language":"C++","gravatar":"https://avatars2.githubusercontent.com/u/1971455?v=3&s=64","followers":0,"stars":0,"organizations":[],"contributions":11,"contributionsStreak":1,"contributionsCurrentStreak":0},{"name":"David Toledo","login":"davitol","location":"Valladolid","language":"","gravatar":"https://avatars1.githubusercontent.com/u/10596560?v=3&s=64","followers":1,"stars":0,"organizations":[],"contributions":10,"contributionsStreak":3,"contributionsCurrentStreak":0},{"name":"Fernando Jordan Silva","login":"fjordansilva","location":"Valladolid, Spain","language":"JavaScript","gravatar":"https://avatars1.githubusercontent.com/u/679038?v=3&s=64","followers":0,"stars":2,"organizations":[],"contributions":10,"contributionsStreak":1,"contributionsCurrentStreak":0},{"name":"","login":"pwnage2apps","location":"Valladolid","language":"HTML","gravatar":"https://avatars1.githubusercontent.com/u/11473953?v=3&s=64","followers":0,"stars":0,"organizations":[],"contributions":10,"contributionsStreak":1,"contributionsCurrentStreak":0},{"name":"Iván González Rincón","login":"ivgorin","location":"Laguna de Duero (Valladolid)","language":"Java","gravatar":"https://avatars3.githubusercontent.com/u/7957948?v=3&s=64","followers":1,"stars":0,"organizations":[],"contributions":8,"contributionsStreak":2,"contributionsCurrentStreak":0},{"name":"Jesús Ángel del Pozo","login":"jesusangel","location":"Valladolid","language":"PHP","gravatar":"https://avatars1.githubusercontent.com/u/207777?v=3&s=64","followers":2,"stars":21,"organizations":[],"contributions":7,"contributionsStreak":2,"contributionsCurrentStreak":0},{"name":"Roberto Ortega","login":"darkmaki","location":"Valladolid, Castilla y León, España","language":"C","gravatar":"https://avatars3.githubusercontent.com/u/10024998?v=3&s=64","followers":3,"stars":0,"organizations":["guiuva"],"contributions":5,"contributionsStreak":1,"contributionsCurrentStreak":0},{"name":"Diego Prados","login":"dprados","location":"Valladolid","language":"Swift","gravatar":"https://avatars1.githubusercontent.com/u/5585384?v=3&s=64","followers":0,"stars":5,"organizations":[],"contributions":5,"contributionsStreak":1,"contributionsCurrentStreak":0},{"name":"Cédric M. Campos","login":"vitaminace33","location":"Valladolid, Spain","language":"Matlab","gravatar":"https://avatars1.githubusercontent.com/u/8283134?v=3&s=64","followers":0,"stars":0,"organizations":[],"contributions":4,"contributionsStreak":2,"contributionsCurrentStreak":0},{"name":"Jairo Velasco","login":"Jairove","location":"Valladolid, Spain.","language":"Python","gravatar":"https://avatars0.githubusercontent.com/u/8361118?v=3&s=64","followers":0,"stars":0,"organizations":[],"contributions":4,"contributionsStreak":1,"contributionsCurrentStreak":0},{"name":"Ignacio Cruzado Nuño","login":"icruzado","location":"Burgos or Valladolid, Spain","language":"Shell","gravatar":"https://avatars2.githubusercontent.com/u/1931910?v=3&s=64","followers":0,"stars":1,"organizations":["Telefonica"],"contributions":4,"contributionsStreak":2,"contributionsCurrentStreak":0},{"name":"José M. Giménez García","login":"chemi2g","location":"Valladolid (Spain)","language":"","gravatar":"https://avatars2.githubusercontent.com/u/3583678?v=3&s=64","followers":0,"stars":0,"organizations":[],"contributions":4,"contributionsStreak":1,"contributionsCurrentStreak":0},{"name":"Alfonso Fernandez","login":"afgar","location":"Valladolid, Spain","language":"PHP","gravatar":"https://avatars3.githubusercontent.com/u/2205032?v=3&s=64","followers":0,"stars":0,"organizations":[],"contributions":3,"contributionsStreak":1,"contributionsCurrentStreak":0},{"name":"Alberto López-Barranco","login":"albelop","location":"Valladolid, Spain","language":"JavaScript","gravatar":"https://avatars2.githubusercontent.com/u/6680018?v=3&s=64","followers":0,"stars":0,"organizations":[],"contributions":3,"contributionsStreak":1,"contributionsCurrentStreak":0},{"name":"@SantiiHoyos","login":"santiihoyos","location":"Valladolid, Spain","language":"Makefile","gravatar":"https://avatars0.githubusercontent.com/u/10730150?v=3&s=64","followers":0,"stars":0,"organizations":[],"contributions":3,"contributionsStreak":1,"contributionsCurrentStreak":0},{"name":"Oscar González","login":"olgonzalez","location":"Valladolid","language":"Perl6 and Kotlin","gravatar":"https://avatars1.githubusercontent.com/u/3243958?v=3&s=64","followers":0,"stars":0,"organizations":[],"contributions":3,"contributionsStreak":1,"contributionsCurrentStreak":0},{"name":"Manuel Terrón","login":"Manupucelano","location":"Valladolid","language":"","gravatar":"https://avatars3.githubusercontent.com/u/10945965?v=3&s=64","followers":0,"stars":0,"organizations":[],"contributions":3,"contributionsStreak":1,"contributionsCurrentStreak":0},{"name":"programaciongalileo","login":"programaciongalileo","location":"Valladolid (Spain)","language":"","gravatar":"https://avatars1.githubusercontent.com/u/7414974?v=3&s=64","followers":0,"stars":0,"organizations":[],"contributions":3,"contributionsStreak":1,"contributionsCurrentStreak":0},{"name":"Grant Croker","login":"grantc","location":"Valladolid, Spain","language":"C","gravatar":"https://avatars1.githubusercontent.com/u/289560?v=3&s=64","followers":0,"stars":5,"organizations":[],"contributions":2,"contributionsStreak":1,"contributionsCurrentStreak":0},{"name":"Alvaro Garcia Loaisa","login":"aloaisa","location":"Valladolid","language":"Groovy","gravatar":"https://avatars2.githubusercontent.com/u/612660?v=3&s=64","followers":16,"stars":12,"organizations":[],"contributions":2,"contributionsStreak":1,"contributionsCurrentStreak":0},{"name":"Andrés Bayón","login":"elektropajo","location":"Valladolid, Spain","language":"ApacheConf","gravatar":"https://avatars2.githubusercontent.com/u/11317202?v=3&s=64","followers":0,"stars":0,"organizations":[],"contributions":2,"contributionsStreak":1,"contributionsCurrentStreak":0},{"name":"Adrián Gil","login":"adriangn","location":"Valladolid, Spain","language":"","gravatar":"https://avatars1.githubusercontent.com/u/8372830?v=3&s=64","followers":0,"stars":0,"organizations":[],"contributions":2,"contributionsStreak":1,"contributionsCurrentStreak":0},{"name":"Jorge","login":"jorgecarabias","location":"Valladolid","language":"Ruby and Java","gravatar":"https://avatars0.githubusercontent.com/u/393588?v=3&s=64","followers":0,"stars":1,"organizations":[],"contributions":1,"contributionsStreak":1,"contributionsCurrentStreak":0},{"name":"archenemy (Fernando G.)","login":"archenemy","location":"Valladolid, Spain","language":"PHP","gravatar":"https://avatars2.githubusercontent.com/u/195672?v=3&s=64","followers":8,"stars":5,"organizations":[],"contributions":1,"contributionsStreak":1,"contributionsCurrentStreak":0},{"name":"Diego R. Llanos","login":"drllanos","location":"Valladolid, Spain","language":"","gravatar":"https://avatars2.githubusercontent.com/u/11043614?v=3&s=64","followers":0,"stars":0,"organizations":[],"contributions":1,"contributionsStreak":1,"contributionsCurrentStreak":0},{"name":"David Medina","login":"copitux","location":"Valladolid, Spain","language":"Python","gravatar":"https://avatars2.githubusercontent.com/u/508027?v=3&s=64","followers":21,"stars":152,"organizations":["Telefonica"],"contributions":1,"contributionsStreak":1,"contributionsCurrentStreak":0},{"name":"David Vicente Fuentes","login":"davicente","location":"Valladolid","language":"","gravatar":"https://avatars1.githubusercontent.com/u/752240?v=3&s=64","followers":0,"stars":0,"organizations":["Telefonica"],"contributions":1,"contributionsStreak":1,"contributionsCurrentStreak":0},{"name":"Javier Royuela del Val","login":"javroyva","location":"Valladolid, Spain.","language":"","gravatar":"https://avatars3.githubusercontent.com/u/3831114?v=3&s=64","followers":0,"stars":0,"organizations":[],"contributions":1,"contributionsStreak":1,"contributionsCurrentStreak":0},{"name":"David","login":"davidrod","location":"Valladolid, Spain","language":"Java","gravatar":"https://avatars1.githubusercontent.com/u/3218834?v=3&s=64","followers":0,"stars":0,"organizations":[],"contributions":1,"contributionsStreak":1,"contributionsCurrentStreak":0},{"name":"Alergant","login":"alergant","location":"Valladolid","language":"PHP","gravatar":"https://avatars1.githubusercontent.com/u/7142269?v=3&s=64","followers":0,"stars":1,"organizations":[],"contributions":1,"contributionsStreak":1,"contributionsCurrentStreak":0}]