[{"name":"Leonardo J. Caballero G.","login":"macagua","location":"Libertador, Mérida, Venezuela","language":"Python","gravatar":"https://avatars0.githubusercontent.com/u/185395?v=3&s=64","followers":110,"stars":25,"organizations":["plone","deliverance","collective","socialplanning","Cenditel","PloneGov","django-ve","pyve","plone-ve","CanaimaGNULinux","Conectivo","Covantec","TLIPEA","PloneEdu"],"contributions":618,"contributionsStreak":21,"contributionsCurrentStreak":0},{"name":"Andrés G. Saravia","login":"andresgsaravia","location":"Mérida","language":"Python","gravatar":"https://avatars2.githubusercontent.com/u/847815?v=3&s=64","followers":7,"stars":18,"organizations":[],"contributions":233,"contributionsStreak":16,"contributionsCurrentStreak":0},{"name":"Mario Ricalde","login":"MarioRicalde","location":"Mérida, México","language":"VimL","gravatar":"https://avatars3.githubusercontent.com/u/125900?v=3&s=64","followers":83,"stars":1865,"organizations":["hybridgroup"],"contributions":172,"contributionsStreak":4,"contributionsCurrentStreak":0},{"name":"Luis Burgos","login":"LuisBurgos","location":"Mérida, Yucatán","language":"Java","gravatar":"https://avatars1.githubusercontent.com/u/7050120?v=3&s=64","followers":3,"stars":0,"organizations":[],"contributions":170,"contributionsStreak":7,"contributionsCurrentStreak":0},{"name":"José Dulanto","login":"josedulanto","location":"Mérida, México","language":"CSS","gravatar":"https://avatars2.githubusercontent.com/u/51538?v=3&s=64","followers":2,"stars":1,"organizations":[],"contributions":133,"contributionsStreak":12,"contributionsCurrentStreak":0},{"name":"Juan Pablo Zamora Veraza","login":"jupazave","location":"Mérida, MEX","language":"CSS","gravatar":"https://avatars0.githubusercontent.com/u/1057196?v=3&s=64","followers":11,"stars":109,"organizations":["QuokkaMX","yellowme","RubyMid"],"contributions":132,"contributionsStreak":4,"contributionsCurrentStreak":0},{"name":"Francisco Palm","login":"map0logo","location":"Mérida, Venezuela","language":"Python","gravatar":"https://avatars0.githubusercontent.com/u/236351?v=3&s=64","followers":12,"stars":589,"organizations":["django-ve","pyve","OpenVE"],"contributions":107,"contributionsStreak":4,"contributionsCurrentStreak":0},{"name":"Javier","login":"javierojeda94","location":"Mérida, Yucatán, México","language":"Java","gravatar":"https://avatars3.githubusercontent.com/u/5795113?v=3&s=64","followers":2,"stars":1,"organizations":[],"contributions":106,"contributionsStreak":3,"contributionsCurrentStreak":0},{"name":"Gastón Sánchez","login":"gaastonsr","location":"Mérida, Yucatán, México","language":"JavaScript","gravatar":"https://avatars2.githubusercontent.com/u/2997285?v=3&s=64","followers":1,"stars":1212,"organizations":[],"contributions":105,"contributionsStreak":5,"contributionsCurrentStreak":0},{"name":"Typson A Sánchez M","login":"styp152","location":"Mérida, Venezuela","language":"JavaScript","gravatar":"https://avatars3.githubusercontent.com/u/241622?v=3&s=64","followers":14,"stars":10,"organizations":["JokteLatinoamerica","uptm","TLIPEA","sanchezsolutions"],"contributions":99,"contributionsStreak":3,"contributionsCurrentStreak":0},{"name":"Wuilliam Lacruz","login":"wuilliam321","location":"Mérida, Venezuela","language":"PHP","gravatar":"https://avatars2.githubusercontent.com/u/236566?v=3&s=64","followers":8,"stars":4,"organizations":[],"contributions":91,"contributionsStreak":6,"contributionsCurrentStreak":0},{"name":"Jeans Michell","login":"JeansLicona","location":"Mérida, Yucatan","language":"PHP","gravatar":"https://avatars0.githubusercontent.com/u/5914416?v=3&s=64","followers":1,"stars":2,"organizations":[],"contributions":81,"contributionsStreak":3,"contributionsCurrentStreak":0},{"name":"Daniel P","login":"daetherius","location":"Mérida, México","language":"PHP","gravatar":"https://avatars1.githubusercontent.com/u/237597?v=3&s=64","followers":3,"stars":710,"organizations":["hybridgroup"],"contributions":66,"contributionsStreak":2,"contributionsCurrentStreak":0},{"name":"Jose V. Alcala-Burgos","login":"vidalalcala","location":"Mérida, México","language":"C++","gravatar":"https://avatars3.githubusercontent.com/u/5065855?v=3&s=64","followers":3,"stars":25,"organizations":[],"contributions":46,"contributionsStreak":3,"contributionsCurrentStreak":0},{"name":"Aldo Arian Castillo","login":"ArianCastillo","location":"Mérida","language":"C","gravatar":"https://avatars1.githubusercontent.com/u/6005226?v=3&s=64","followers":1,"stars":1,"organizations":[],"contributions":38,"contributionsStreak":3,"contributionsCurrentStreak":0},{"name":"Luis Ramos","login":"luissquall","location":"Mérida, México","language":"JavaScript","gravatar":"https://avatars2.githubusercontent.com/u/28030?v=3&s=64","followers":6,"stars":799,"organizations":["affenbits"],"contributions":35,"contributionsStreak":3,"contributionsCurrentStreak":0},{"name":"Jesús Gutiérrez Cortazar","login":"JGutierrezC","location":"Mérida, México","language":"Ruby","gravatar":"https://avatars2.githubusercontent.com/u/5317696?v=3&s=64","followers":1,"stars":546,"organizations":[],"contributions":32,"contributionsStreak":4,"contributionsCurrentStreak":0},{"name":"Develoteca","login":"oscaruhp","location":"Mérida","language":"","gravatar":"https://avatars3.githubusercontent.com/u/859116?v=3&s=64","followers":1,"stars":0,"organizations":[],"contributions":31,"contributionsStreak":1,"contributionsCurrentStreak":0},{"name":"Miki Balboa","login":"miguelbalboa","location":"Mérida, Yucatán.","language":"Arduino and C++","gravatar":"https://avatars3.githubusercontent.com/u/971880?v=3&s=64","followers":24,"stars":233,"organizations":[],"contributions":28,"contributionsStreak":2,"contributionsCurrentStreak":0},{"name":"Juan Carlos Peña Moreno","login":"pegnacorp","location":"Mérida, Yucatán","language":"Java","gravatar":"https://avatars0.githubusercontent.com/u/5620224?v=3&s=64","followers":1,"stars":0,"organizations":[],"contributions":26,"contributionsStreak":6,"contributionsCurrentStreak":0},{"name":"J. Hernán Ramírez R","login":"hernanramirez","location":"Mérida, Venezuela","language":"PHP","gravatar":"https://avatars3.githubusercontent.com/u/3480478?v=3&s=64","followers":1,"stars":16,"organizations":[],"contributions":19,"contributionsStreak":2,"contributionsCurrentStreak":0},{"name":"Carlos Paparoni","login":"kenshin23","location":"Mérida, Venezuela","language":"Shell","gravatar":"https://avatars2.githubusercontent.com/u/1142320?v=3&s=64","followers":1,"stars":1339,"organizations":["DesarrolladoresDeVenezuela"],"contributions":15,"contributionsStreak":4,"contributionsCurrentStreak":0},{"name":"José L. Redrejo Rodríguez","login":"jredrejo","location":"Mérida - Spain","language":"Shell","gravatar":"https://avatars1.githubusercontent.com/u/1008178?v=3&s=64","followers":2,"stars":5,"organizations":[],"contributions":15,"contributionsStreak":2,"contributionsCurrentStreak":0},{"name":"Gerardo J. Vasquez R.","login":"codebio","location":"Mérida, Venezuela","language":"Python","gravatar":"https://avatars0.githubusercontent.com/u/3824195?v=3&s=64","followers":4,"stars":1,"organizations":[],"contributions":14,"contributionsStreak":2,"contributionsCurrentStreak":0},{"name":"José A. Márquez R","login":"joseangelmr","location":"Mérida-Venezuela","language":"C#","gravatar":"https://avatars2.githubusercontent.com/u/3728822?v=3&s=64","followers":3,"stars":1,"organizations":[],"contributions":10,"contributionsStreak":2,"contributionsCurrentStreak":0},{"name":"Laudin Alessandro Molina","login":"lmolina","location":"Mérida/Venezuela","language":"C++","gravatar":"https://avatars3.githubusercontent.com/u/107266?v=3&s=64","followers":8,"stars":4,"organizations":[],"contributions":6,"contributionsStreak":1,"contributionsCurrentStreak":0},{"name":"Rubén Espadas","login":"respadas","location":"Mérida, Yucatán","language":"Shell","gravatar":"https://avatars1.githubusercontent.com/u/755085?v=3&s=64","followers":1,"stars":32,"organizations":[],"contributions":5,"contributionsStreak":1,"contributionsCurrentStreak":0},{"name":"Eduardo Reyes","login":"EduardoRT","location":"Mérida","language":"","gravatar":"https://avatars2.githubusercontent.com/u/1114422?v=3&s=64","followers":5,"stars":1,"organizations":[],"contributions":5,"contributionsStreak":1,"contributionsCurrentStreak":0},{"name":"J. Armando Uch","login":"jahrmando","location":"Mérida, Yucatán","language":"Shell","gravatar":"https://avatars2.githubusercontent.com/u/386584?v=3&s=64","followers":3,"stars":1,"organizations":[],"contributions":4,"contributionsStreak":1,"contributionsCurrentStreak":0},{"name":"Luis Felipe Boscan Nava","login":"lfbos","location":"Mérida - Venezuela","language":"","gravatar":"https://avatars3.githubusercontent.com/u/5703286?v=3&s=64","followers":1,"stars":0,"organizations":[],"contributions":3,"contributionsStreak":1,"contributionsCurrentStreak":0},{"name":"Axel Cureño","login":"Axelcureno","location":"Mérida, Yucatán.","language":"JavaScript","gravatar":"https://avatars2.githubusercontent.com/u/1179549?v=3&s=64","followers":1,"stars":1,"organizations":[],"contributions":3,"contributionsStreak":1,"contributionsCurrentStreak":0},{"name":"josue","login":"mehanika","location":"Mérida, Yucatán, México","language":"JavaScript","gravatar":"https://avatars0.githubusercontent.com/u/318978?v=3&s=64","followers":1,"stars":1,"organizations":[],"contributions":3,"contributionsStreak":1,"contributionsCurrentStreak":0},{"name":"Alberto José Medrano Villalobos","login":"ajmv","location":"Mérida, Venezuela","language":"","gravatar":"https://avatars3.githubusercontent.com/u/161396?v=3&s=64","followers":1,"stars":1,"organizations":[],"contributions":3,"contributionsStreak":1,"contributionsCurrentStreak":0},{"name":"Russel de Jesus Cruz Rodriguez","login":"ruscruzel","location":"Mérida","language":"JavaScript","gravatar":"https://avatars0.githubusercontent.com/u/4977448?v=3&s=64","followers":8,"stars":4,"organizations":[],"contributions":2,"contributionsStreak":1,"contributionsCurrentStreak":0},{"name":"Jorge Carmona","login":"atomicum","location":"Mérida","language":"","gravatar":"https://avatars2.githubusercontent.com/u/6386399?v=3&s=64","followers":2,"stars":0,"organizations":[],"contributions":1,"contributionsStreak":1,"contributionsCurrentStreak":0},{"name":"Alberto Cabeza","login":"alberto-cabeza","location":"Mérida","language":"","gravatar":"https://avatars1.githubusercontent.com/u/6225528?v=3&s=64","followers":2,"stars":9,"organizations":[],"contributions":1,"contributionsStreak":1,"contributionsCurrentStreak":0},{"name":"Genarby Guiseppe Peña","login":"genarby","location":"Mérida, Venezuela","language":"Python","gravatar":"https://avatars0.githubusercontent.com/u/3833905?v=3&s=64","followers":2,"stars":1,"organizations":[],"contributions":1,"contributionsStreak":1,"contributionsCurrentStreak":0}]