[{"name":"Daniel","login":"DaniAV","location":"León","language":"Java","gravatar":"https://avatars0.githubusercontent.com/u/8928270?v=3&s=64","followers":0,"user_stars":"0","stars":0,"organizations":[],"contributions":118,"contributionsStreak":5,"contributionsCurrentStreak":0},{"name":"Roberto Santalla","login":"roobre","location":"León, Spain","language":"PHP","gravatar":"https://avatars1.githubusercontent.com/u/969721?v=3&s=64","followers":6,"user_stars":"34","stars":12,"organizations":[],"contributions":116,"contributionsStreak":5,"contributionsCurrentStreak":0},{"name":"Montse Chamorro","login":"montsechamorro","location":"León","language":"Java","gravatar":"https://avatars3.githubusercontent.com/u/8928284?v=3&s=64","followers":0,"user_stars":"0","stars":0,"organizations":[],"contributions":85,"contributionsStreak":4,"contributionsCurrentStreak":0},{"name":"Pedro Macías","login":"Libertual","location":"León, Spain","language":"JavaScript","gravatar":"https://avatars2.githubusercontent.com/u/9809302?v=3&s=64","followers":2,"user_stars":"20","stars":0,"organizations":[],"contributions":79,"contributionsStreak":5,"contributionsCurrentStreak":0},{"name":"Pablo Rodríguez Robles","login":"PabloRdrRbl","location":"León (Spain)","language":"Python","gravatar":"https://avatars2.githubusercontent.com/u/7204331?v=3&s=64","followers":5,"user_stars":"14","stars":7,"organizations":[],"contributions":74,"contributionsStreak":8,"contributionsCurrentStreak":0},{"name":"gut-mart","login":"gut-mart","location":"León(Spain)","language":"Python","gravatar":"https://avatars0.githubusercontent.com/u/11340293?v=3&s=64","followers":0,"user_stars":"3","stars":0,"organizations":[],"contributions":61,"contributionsStreak":5,"contributionsCurrentStreak":0},{"name":"Pablo Jimenez Tocino","login":"pablo0910","location":"Salamanca, Castilla y León, Spain","language":"C and Java","gravatar":"https://avatars2.githubusercontent.com/u/10597157?v=3&s=64","followers":0,"user_stars":"0","stars":0,"organizations":[],"contributions":56,"contributionsStreak":2,"contributionsCurrentStreak":0},{"name":"Julia Zuara Jimenez","login":"pizcogirl","location":"León","language":"Java","gravatar":"https://avatars1.githubusercontent.com/u/8928281?v=3&s=64","followers":0,"user_stars":"2","stars":0,"organizations":[],"contributions":55,"contributionsStreak":2,"contributionsCurrentStreak":0},{"name":"Alba Del Amo","login":"aamoga00","location":"León","language":"Java and CSS","gravatar":"https://avatars1.githubusercontent.com/u/8928265?v=3&s=64","followers":0,"user_stars":"0","stars":0,"organizations":[],"contributions":39,"contributionsStreak":2,"contributionsCurrentStreak":0},{"name":"Soraya Flecha de la Puente","login":"SorayaFlecha","location":"León","language":"Java","gravatar":"https://avatars3.githubusercontent.com/u/8928260?v=3&s=64","followers":1,"user_stars":"0","stars":0,"organizations":[],"contributions":32,"contributionsStreak":3,"contributionsCurrentStreak":0},{"name":"Alejandro Rodríguez Monge","login":"Dharryn","location":"León, Spain","language":"Python","gravatar":"https://avatars0.githubusercontent.com/u/9396382?v=3&s=64","followers":3,"user_stars":"1","stars":3,"organizations":[],"contributions":29,"contributionsStreak":1,"contributionsCurrentStreak":0},{"name":"Eloy García Almadén","login":"egara","location":"León, Spain","language":"CMake","gravatar":"https://avatars3.githubusercontent.com/u/13696843?v=3&s=64","followers":0,"user_stars":"0","stars":0,"organizations":[],"contributions":25,"contributionsStreak":4,"contributionsCurrentStreak":0},{"name":"Guillermo Santos Melgar","login":"NeoMorfeo","location":"León, Spain","language":"Shell","gravatar":"https://avatars1.githubusercontent.com/u/3766333?v=3&s=64","followers":4,"user_stars":"62","stars":1,"organizations":[],"contributions":17,"contributionsStreak":2,"contributionsCurrentStreak":0},{"name":"Joseph Carvajal Deffitt","login":"carvajal003","location":"León, Spain","language":"JavaScript and CSS","gravatar":"https://avatars1.githubusercontent.com/u/11072825?v=3&s=64","followers":0,"user_stars":"0","stars":1,"organizations":[],"contributions":16,"contributionsStreak":1,"contributionsCurrentStreak":0},{"name":"Jorge Alonso Gómez","login":"JorgeAlonsoGomez","location":"Salamanca, Castilla y León, España","language":"C#","gravatar":"https://avatars0.githubusercontent.com/u/12047150?v=3&s=64","followers":0,"user_stars":"0","stars":0,"organizations":[],"contributions":16,"contributionsStreak":5,"contributionsCurrentStreak":0},{"name":"Borja Merino","login":"BorjaMerino","location":"Spain (León)","language":"Python","gravatar":"https://avatars2.githubusercontent.com/u/1701534?v=3&s=64","followers":31,"user_stars":"23","stars":19,"organizations":[],"contributions":13,"contributionsStreak":1,"contributionsCurrentStreak":0},{"name":"Alfonso Sánchez González","login":"unPoncho","location":"León","language":"PHP","gravatar":"https://avatars1.githubusercontent.com/u/1320670?v=3&s=64","followers":3,"user_stars":"2","stars":0,"organizations":[],"contributions":13,"contributionsStreak":2,"contributionsCurrentStreak":0},{"name":"Roberto Ortega","login":"darkmaki","location":"Valladolid, Castilla y León, España","language":"C and Java","gravatar":"https://avatars3.githubusercontent.com/u/10024998?v=3&s=64","followers":3,"user_stars":"0","stars":0,"organizations":[],"contributions":12,"contributionsStreak":2,"contributionsCurrentStreak":0},{"name":"Rober de Castro","login":"roberdcr","location":"León","language":"Java","gravatar":"https://avatars1.githubusercontent.com/u/6849195?v=3&s=64","followers":1,"user_stars":"0","stars":0,"organizations":[],"contributions":10,"contributionsStreak":1,"contributionsCurrentStreak":0},{"name":"Sebas MGC","login":"agrogeek","location":"Arroyomolinos de León, Huelva","language":"PHP","gravatar":"https://avatars3.githubusercontent.com/u/69480?v=3&s=64","followers":0,"user_stars":"20","stars":2,"organizations":[],"contributions":10,"contributionsStreak":1,"contributionsCurrentStreak":0},{"name":"Alfonso Abella","login":"aabella","location":"León, Spain","language":"C++","gravatar":"https://avatars0.githubusercontent.com/u/1281929?v=3&s=64","followers":1,"user_stars":"3","stars":22,"organizations":[],"contributions":9,"contributionsStreak":2,"contributionsCurrentStreak":0},{"name":"Cristian Tabuyo","login":"ctabuyo","location":"León, Spain","language":"C#","gravatar":"https://avatars2.githubusercontent.com/u/13765677?v=3&s=64","followers":1,"user_stars":"0","stars":0,"organizations":[],"contributions":7,"contributionsStreak":1,"contributionsCurrentStreak":0},{"name":"Jonathan","login":"jonathanrg","location":"León","language":"CSS","gravatar":"https://avatars1.githubusercontent.com/u/6638160?v=3&s=64","followers":1,"user_stars":"0","stars":0,"organizations":[],"contributions":4,"contributionsStreak":2,"contributionsCurrentStreak":0},{"name":"David Alvarez","login":"davidalfe","location":"León, Spain","language":"","gravatar":"https://avatars0.githubusercontent.com/u/3811072?v=3&s=64","followers":1,"user_stars":"1","stars":0,"organizations":[],"contributions":4,"contributionsStreak":1,"contributionsCurrentStreak":0},{"name":"Jorge Valencia","login":"jorgeuve","location":"León, Spain","language":"Perl","gravatar":"https://avatars1.githubusercontent.com/u/726703?v=3&s=64","followers":1,"user_stars":"2","stars":2,"organizations":[],"contributions":3,"contributionsStreak":1,"contributionsCurrentStreak":0},{"name":"Carlos J. Casares","login":"casares","location":"León, España","language":"Java","gravatar":"https://avatars0.githubusercontent.com/u/11679030?v=3&s=64","followers":1,"user_stars":"0","stars":0,"organizations":[],"contributions":3,"contributionsStreak":1,"contributionsCurrentStreak":0},{"name":"","login":"fjrodriguezcom","location":"León, Spain","language":"Shell","gravatar":"https://avatars2.githubusercontent.com/u/1823531?v=3&s=64","followers":0,"user_stars":"9","stars":1,"organizations":[],"contributions":1,"contributionsStreak":1,"contributionsCurrentStreak":0},{"name":"Aristóteles Federico Núñez Juárez","login":"aristoteles-nunez","location":"Huajuapan de León, Oaxaca","language":"Python","gravatar":"https://avatars1.githubusercontent.com/u/12948594?v=3&s=64","followers":0,"user_stars":"0","stars":0,"organizations":[],"contributions":1,"contributionsStreak":1,"contributionsCurrentStreak":0},{"name":"Víctor Rodríguez","login":"VictorRodriguez-ULE","location":"León, Spain","language":"","gravatar":"https://avatars1.githubusercontent.com/u/7995366?v=3&s=64","followers":0,"user_stars":"0","stars":0,"organizations":[],"contributions":1,"contributionsStreak":1,"contributionsCurrentStreak":0},{"name":"Jose J. Fernández","login":"josejfernandez","location":"León, Spain","language":"PHP and C","gravatar":"https://avatars1.githubusercontent.com/u/1663138?v=3&s=64","followers":1,"user_stars":"17","stars":0,"organizations":[],"contributions":1,"contributionsStreak":1,"contributionsCurrentStreak":0}]