[{"name":"Kiko Beats","login":"Kikobeats","location":"Murcia, Spain","language":"JavaScript","gravatar":"https://avatars0.githubusercontent.com/u/2096101?v=3&s=64","followers":82,"user_stars":"322","stars":306,"organizations":["zombts","sailorjs","parrotjs"],"contributions":2078,"contributionsStreak":71,"contributionsCurrentStreak":37},{"name":"Elena Torró","login":"elenatorro","location":"Murcia / Alicante / Salzburg","language":"JavaScript","gravatar":"https://avatars3.githubusercontent.com/u/3824953?v=3&s=64","followers":61,"user_stars":"30","stars":16,"organizations":[],"contributions":1162,"contributionsStreak":62,"contributionsCurrentStreak":0},{"name":"Pedro Palazón Candel","login":"kusor","location":"Murcia (Spain)","language":"JavaScript","gravatar":"https://avatars1.githubusercontent.com/u/13474?v=3&s=64","followers":44,"user_stars":"50","stars":209,"organizations":["joyent"],"contributions":805,"contributionsStreak":6,"contributionsCurrentStreak":0},{"name":"Matthew Vincent","login":"neshmi","location":"Murcia, Spain","language":"Ruby","gravatar":"https://avatars0.githubusercontent.com/u/7353?v=3&s=64","followers":1,"user_stars":"47","stars":51,"organizations":["OpenDig"],"contributions":178,"contributionsStreak":5,"contributionsCurrentStreak":0},{"name":"Juan Jose Perez Castejon","login":"jjpcaste","location":"Murcia - España (Spain)","language":"","gravatar":"https://avatars1.githubusercontent.com/u/7204052?v=3&s=64","followers":0,"user_stars":"0","stars":0,"organizations":[],"contributions":160,"contributionsStreak":41,"contributionsCurrentStreak":3},{"name":"Raul Sanchez","login":"RaulKite","location":"Murcia (Spain)","language":"Ruby","gravatar":"https://avatars1.githubusercontent.com/u/1314992?v=3&s=64","followers":3,"user_stars":"32","stars":5,"organizations":[],"contributions":135,"contributionsStreak":5,"contributionsCurrentStreak":0},{"name":"Eduardo Rey Jara","login":"SedueRey","location":"Murcia","language":"Ruby","gravatar":"https://avatars0.githubusercontent.com/u/3238226?v=3&s=64","followers":1,"user_stars":"19","stars":0,"organizations":[],"contributions":129,"contributionsStreak":11,"contributionsCurrentStreak":0},{"name":"Adrián Lomas","login":"glomadrian","location":"Murcia, Spain","language":"Java","gravatar":"https://avatars1.githubusercontent.com/u/5353046?v=3&s=64","followers":50,"user_stars":"87","stars":646,"organizations":["fistbumpteam","FineCinnamon"],"contributions":91,"contributionsStreak":5,"contributionsCurrentStreak":0},{"name":"Siro Díaz Palazón","login":"SiroDiaz","location":"Murcia, Spain","language":"PHP","gravatar":"https://avatars3.githubusercontent.com/u/7469286?v=3&s=64","followers":2,"user_stars":"102","stars":5,"organizations":[],"contributions":83,"contributionsStreak":7,"contributionsCurrentStreak":0},{"name":"Toni Wang","login":"TonyWang-UMU","location":"Murcia, España","language":"Java and C++","gravatar":"https://avatars3.githubusercontent.com/u/7012694?v=3&s=64","followers":1,"user_stars":"0","stars":0,"organizations":[],"contributions":59,"contributionsStreak":6,"contributionsCurrentStreak":0},{"name":"Juan Riquelme","login":"soulchainer","location":"Murcia","language":"JavaScript","gravatar":"https://avatars3.githubusercontent.com/u/169524?v=3&s=64","followers":5,"user_stars":"105","stars":3,"organizations":[],"contributions":54,"contributionsStreak":2,"contributionsCurrentStreak":0},{"name":"Electrónica divertida","login":"electronicadivertida","location":"Molina Segura, Murcia, España","language":"Arduino","gravatar":"https://avatars1.githubusercontent.com/u/9558169?v=3&s=64","followers":1,"user_stars":"0","stars":8,"organizations":[],"contributions":52,"contributionsStreak":2,"contributionsCurrentStreak":0},{"name":"Guillermo Fernández","login":"guillermofr","location":"Murcia , Spain","language":"PHP","gravatar":"https://avatars2.githubusercontent.com/u/1298429?v=3&s=64","followers":3,"user_stars":"7","stars":2,"organizations":[],"contributions":48,"contributionsStreak":4,"contributionsCurrentStreak":0},{"name":"Miguel Ángel Ortuño","login":"ortuman","location":"Murcia","language":"Swift","gravatar":"https://avatars1.githubusercontent.com/u/888899?v=3&s=64","followers":11,"user_stars":"2","stars":511,"organizations":[],"contributions":45,"contributionsStreak":2,"contributionsCurrentStreak":0},{"name":"José Antonio De La Fuente Brando","login":"delafuente28","location":"Murcia (Spain)","language":"JavaScript","gravatar":"https://avatars2.githubusercontent.com/u/10086748?v=3&s=64","followers":1,"user_stars":"0","stars":0,"organizations":[],"contributions":44,"contributionsStreak":3,"contributionsCurrentStreak":0},{"name":"Miguel Angel Martinez Cifuentes","login":"Icebox2","location":"Murcia","language":"","gravatar":"https://avatars2.githubusercontent.com/u/8926430?v=3&s=64","followers":1,"user_stars":"1","stars":0,"organizations":[],"contributions":42,"contributionsStreak":6,"contributionsCurrentStreak":0},{"name":"Rubén Simón Andreo","login":"neomede","location":"Totana, Murcia","language":"PHP","gravatar":"https://avatars1.githubusercontent.com/u/4903669?v=3&s=64","followers":10,"user_stars":"116","stars":6,"organizations":[],"contributions":39,"contributionsStreak":3,"contributionsCurrentStreak":0},{"name":"Jose Luis López López","login":"Jose3L","location":"Alhama de Murcia, España","language":"Ruby","gravatar":"https://avatars1.githubusercontent.com/u/8429018?v=3&s=64","followers":2,"user_stars":"0","stars":0,"organizations":[],"contributions":35,"contributionsStreak":4,"contributionsCurrentStreak":0},{"name":"José Luis Martín","login":"jlmd","location":"Murcia, Spain","language":"Java","gravatar":"https://avatars1.githubusercontent.com/u/6186326?v=3&s=64","followers":32,"user_stars":"91","stars":363,"organizations":["fistbumpteam","FineCinnamon"],"contributions":34,"contributionsStreak":3,"contributionsCurrentStreak":0},{"name":"Pedro Mateo","login":"pedromateo","location":"Murcia, Spain","language":"Java","gravatar":"https://avatars1.githubusercontent.com/u/3541523?v=3&s=64","followers":4,"user_stars":"0","stars":7,"organizations":["catedrasaes-umu"],"contributions":26,"contributionsStreak":1,"contributionsCurrentStreak":0},{"name":"Angel L. Mateo","login":"amateo","location":"Murcia (Spain)","language":"Ruby","gravatar":"https://avatars0.githubusercontent.com/u/3133951?v=3&s=64","followers":0,"user_stars":"1","stars":0,"organizations":[],"contributions":25,"contributionsStreak":2,"contributionsCurrentStreak":0},{"name":"Ángel Luis","login":"RdlP","location":"Murcia","language":"Python","gravatar":"https://avatars3.githubusercontent.com/u/1231721?v=3&s=64","followers":1,"user_stars":"8","stars":4,"organizations":[],"contributions":24,"contributionsStreak":2,"contributionsCurrentStreak":0},{"name":"Juanjo","login":"Juanjofp","location":"Murcia, Spain","language":"JavaScript","gravatar":"https://avatars0.githubusercontent.com/u/446496?v=3&s=64","followers":0,"user_stars":"6","stars":0,"organizations":[],"contributions":23,"contributionsStreak":1,"contributionsCurrentStreak":0},{"name":"OpenStack + Broker Project","login":"OpenMurVDI","location":"Murcia, Spain","language":"Ruby","gravatar":"https://avatars3.githubusercontent.com/u/7744656?v=3&s=64","followers":7,"user_stars":"0","stars":1,"organizations":[],"contributions":23,"contributionsStreak":1,"contributionsCurrentStreak":0},{"name":"Pablo C.M.","login":"pablocm-aserti","location":"Espinardo, Murcia","language":"Python","gravatar":"https://avatars2.githubusercontent.com/u/8291685?v=3&s=64","followers":0,"user_stars":"0","stars":0,"organizations":[],"contributions":23,"contributionsStreak":1,"contributionsCurrentStreak":0},{"name":"Daniel Vigueras","login":"dvigueras","location":"Murcia","language":"Go","gravatar":"https://avatars0.githubusercontent.com/u/352689?v=3&s=64","followers":27,"user_stars":"91","stars":0,"organizations":["scalia"],"contributions":21,"contributionsStreak":2,"contributionsCurrentStreak":0},{"name":"Alberto López Sánchez","login":"Earthlandto","location":"Murcia, ES","language":"CSS","gravatar":"https://avatars0.githubusercontent.com/u/9001691?v=3&s=64","followers":2,"user_stars":"4","stars":0,"organizations":[],"contributions":20,"contributionsStreak":2,"contributionsCurrentStreak":0},{"name":"Francisco Javier López","login":"fjsanpedro","location":"Murcia (Spain)","language":"Ruby","gravatar":"https://avatars3.githubusercontent.com/u/4815974?v=3&s=64","followers":4,"user_stars":"1","stars":16,"organizations":[],"contributions":19,"contributionsStreak":1,"contributionsCurrentStreak":0},{"name":"Gabri","login":"Gabriel-fm","location":"Murcia, Spain","language":"TeX and Java","gravatar":"https://avatars0.githubusercontent.com/u/651324?v=3&s=64","followers":0,"user_stars":"11","stars":0,"organizations":[],"contributions":19,"contributionsStreak":2,"contributionsCurrentStreak":0},{"name":"Nico Fantino","login":"ala747","location":"Murcia, SPAIN","language":"PHP","gravatar":"https://avatars2.githubusercontent.com/u/162955?v=3&s=64","followers":8,"user_stars":"27","stars":9,"organizations":[],"contributions":19,"contributionsStreak":3,"contributionsCurrentStreak":0},{"name":"Gabriel","login":"gabrielperales","location":"Murcia","language":"JavaScript","gravatar":"https://avatars3.githubusercontent.com/u/1859128?v=3&s=64","followers":20,"user_stars":"166","stars":1,"organizations":[],"contributions":18,"contributionsStreak":2,"contributionsCurrentStreak":0},{"name":"Alejandro Perez","login":"alejandro-perez","location":"Murcia, Spain","language":"Python","gravatar":"https://avatars2.githubusercontent.com/u/2082536?v=3&s=64","followers":1,"user_stars":"2","stars":1,"organizations":[],"contributions":15,"contributionsStreak":1,"contributionsCurrentStreak":0},{"name":"Juan Eduardo","login":"dard0","location":"Murcia","language":"Java","gravatar":"https://avatars3.githubusercontent.com/u/2410625?v=3&s=64","followers":9,"user_stars":"0","stars":0,"organizations":[],"contributions":14,"contributionsStreak":2,"contributionsCurrentStreak":0},{"name":"Josue Martinez","login":"Jmartnz","location":"Murcia, Spain","language":"Ruby","gravatar":"https://avatars1.githubusercontent.com/u/9195159?v=3&s=64","followers":1,"user_stars":"71","stars":0,"organizations":[],"contributions":13,"contributionsStreak":3,"contributionsCurrentStreak":0},{"name":"Adrián Egea Comenge","login":"AdrianECom","location":"Murcia, Spain","language":"Java","gravatar":"https://avatars1.githubusercontent.com/u/8566870?v=3&s=64","followers":4,"user_stars":"1","stars":0,"organizations":[],"contributions":13,"contributionsStreak":3,"contributionsCurrentStreak":0},{"name":"Miguel del Amor Herrera","login":"forlayo","location":"Murcia","language":"Java","gravatar":"https://avatars0.githubusercontent.com/u/1199238?v=3&s=64","followers":2,"user_stars":"32","stars":2,"organizations":[],"contributions":12,"contributionsStreak":2,"contributionsCurrentStreak":0},{"name":"Fran Gomez","login":"selim37th","location":"Murcia","language":"PHP","gravatar":"https://avatars3.githubusercontent.com/u/8425356?v=3&s=64","followers":0,"user_stars":"0","stars":0,"organizations":[],"contributions":11,"contributionsStreak":3,"contributionsCurrentStreak":0},{"name":"Andrés Brugarolas","login":"Brugarolas","location":"Murcia, Spain","language":"","gravatar":"https://avatars0.githubusercontent.com/u/6209792?v=3&s=64","followers":2,"user_stars":"13","stars":0,"organizations":[],"contributions":10,"contributionsStreak":2,"contributionsCurrentStreak":0},{"name":"Javier Zapata","login":"javiertic","location":"Murcia, Europe","language":"JavaScript","gravatar":"https://avatars3.githubusercontent.com/u/2348662?v=3&s=64","followers":0,"user_stars":"0","stars":0,"organizations":[],"contributions":9,"contributionsStreak":1,"contributionsCurrentStreak":0},{"name":"Eduardo Ruiz","login":"EduardoRG","location":"Murcia, Spain","language":"Java","gravatar":"https://avatars3.githubusercontent.com/u/7536780?v=3&s=64","followers":0,"user_stars":"0","stars":0,"organizations":[],"contributions":9,"contributionsStreak":2,"contributionsCurrentStreak":0},{"name":"Antonio Maurandi L","login":"amaurandi","location":"Murcia, Spain","language":"","gravatar":"https://avatars1.githubusercontent.com/u/6379656?v=3&s=64","followers":0,"user_stars":"0","stars":0,"organizations":[],"contributions":9,"contributionsStreak":3,"contributionsCurrentStreak":0},{"name":"David","login":"davidfdezros","location":"Murcia, Spain","language":"","gravatar":"https://avatars2.githubusercontent.com/u/8007584?v=3&s=64","followers":2,"user_stars":"0","stars":0,"organizations":[],"contributions":9,"contributionsStreak":2,"contributionsCurrentStreak":0},{"name":"David Lozano Campillo","login":"DavidLC102000","location":"Molina de Segura, Murcia, Spain","language":"Python","gravatar":"https://avatars1.githubusercontent.com/u/10256189?v=3&s=64","followers":0,"user_stars":"0","stars":0,"organizations":[],"contributions":9,"contributionsStreak":1,"contributionsCurrentStreak":0},{"name":"Miguel Manzano García","login":"mmanzano","location":"Murcia, España","language":"CSS","gravatar":"https://avatars3.githubusercontent.com/u/1055699?v=3&s=64","followers":1,"user_stars":"0","stars":0,"organizations":[],"contributions":9,"contributionsStreak":1,"contributionsCurrentStreak":0},{"name":"Benja","login":"benja-ct","location":"Cartagena (Murcia) - Spain","language":"R","gravatar":"https://avatars0.githubusercontent.com/u/7771383?v=3&s=64","followers":0,"user_stars":"0","stars":0,"organizations":[],"contributions":8,"contributionsStreak":1,"contributionsCurrentStreak":0},{"name":"Francisco Jesús Rubio Reales","login":"rubio","location":"Murcia","language":"Shell and Python","gravatar":"https://avatars0.githubusercontent.com/u/1300882?v=3&s=64","followers":3,"user_stars":"7","stars":1,"organizations":[],"contributions":8,"contributionsStreak":1,"contributionsCurrentStreak":0},{"name":"Manuel Forcén Muñoz","login":"Mforcen","location":"Cartagena, Murcia (Spain)","language":"Shell","gravatar":"https://avatars3.githubusercontent.com/u/561011?v=3&s=64","followers":0,"user_stars":"0","stars":0,"organizations":[],"contributions":8,"contributionsStreak":2,"contributionsCurrentStreak":0},{"name":"Inma Bermejo","login":"inmabermejo","location":"Murcia, Spain","language":"JavaScript","gravatar":"https://avatars1.githubusercontent.com/u/902659?v=3&s=64","followers":5,"user_stars":"4","stars":2,"organizations":[],"contributions":7,"contributionsStreak":1,"contributionsCurrentStreak":0},{"name":"","login":"tolemac","location":"Murcia, Spain","language":"JavaScript","gravatar":"https://avatars0.githubusercontent.com/u/247167?v=3&s=64","followers":0,"user_stars":"1","stars":0,"organizations":[],"contributions":6,"contributionsStreak":3,"contributionsCurrentStreak":0},{"name":"Iñaki","login":"igsoblechero","location":"Murcia","language":"Shell","gravatar":"https://avatars0.githubusercontent.com/u/3329998?v=3&s=64","followers":0,"user_stars":"2","stars":0,"organizations":[],"contributions":6,"contributionsStreak":2,"contributionsCurrentStreak":0},{"name":"Diego Sevilla Ruiz","login":"dsevilla","location":"Murcia, Spain","language":"Emacs Lisp","gravatar":"https://avatars1.githubusercontent.com/u/154110?v=3&s=64","followers":11,"user_stars":"122","stars":16,"organizations":[],"contributions":6,"contributionsStreak":1,"contributionsCurrentStreak":0},{"name":"Jesús Perera Aracil","login":"egosum","location":"Murcia","language":"R","gravatar":"https://avatars2.githubusercontent.com/u/1222280?v=3&s=64","followers":6,"user_stars":"1","stars":0,"organizations":[],"contributions":6,"contributionsStreak":1,"contributionsCurrentStreak":0},{"name":"Miguel García","login":"MiguelGL","location":"Murcia, Spain","language":"Java","gravatar":"https://avatars3.githubusercontent.com/u/642181?v=3&s=64","followers":3,"user_stars":"120","stars":0,"organizations":[],"contributions":6,"contributionsStreak":1,"contributionsCurrentStreak":0},{"name":"José Illán","login":"joseillan","location":"Murcia, Spain","language":"Ruby","gravatar":"https://avatars0.githubusercontent.com/u/8101780?v=3&s=64","followers":1,"user_stars":"0","stars":1,"organizations":[],"contributions":5,"contributionsStreak":1,"contributionsCurrentStreak":0},{"name":"Juan Carrión Molina","login":"jufracamo","location":"Murcia, España","language":"","gravatar":"https://avatars0.githubusercontent.com/u/6473248?v=3&s=64","followers":0,"user_stars":"2","stars":0,"organizations":[],"contributions":4,"contributionsStreak":1,"contributionsCurrentStreak":0},{"name":"David Zamora","login":"Dazag","location":"Murcia, España","language":"PHP","gravatar":"https://avatars1.githubusercontent.com/u/1424832?v=3&s=64","followers":1,"user_stars":"32","stars":1,"organizations":[],"contributions":4,"contributionsStreak":1,"contributionsCurrentStreak":0},{"name":"160World","login":"160world","location":"Murcia- Spain","language":"JavaScript","gravatar":"https://avatars2.githubusercontent.com/u/2196964?v=3&s=64","followers":0,"user_stars":"0","stars":0,"organizations":[],"contributions":4,"contributionsStreak":1,"contributionsCurrentStreak":0},{"name":"Open Source Virtual Desktop Infrastructure made Easy","login":"StackVDI","location":"Murcia, Spain","language":"Ruby","gravatar":"https://avatars1.githubusercontent.com/u/7987541?v=3&s=64","followers":8,"user_stars":"0","stars":8,"organizations":[],"contributions":4,"contributionsStreak":2,"contributionsCurrentStreak":0},{"name":"Joaquín Martínez Gadea","login":"joaquinmgadea","location":"Murcia","language":"JavaScript","gravatar":"https://avatars1.githubusercontent.com/u/5854341?v=3&s=64","followers":0,"user_stars":"0","stars":0,"organizations":[],"contributions":4,"contributionsStreak":1,"contributionsCurrentStreak":0},{"name":"Alejandro Cano Pagan","login":"alexcano","location":"Murcia","language":"","gravatar":"https://avatars0.githubusercontent.com/u/10582725?v=3&s=64","followers":0,"user_stars":"1","stars":0,"organizations":[],"contributions":3,"contributionsStreak":1,"contributionsCurrentStreak":0},{"name":"Antonio Gil Espinosa","login":"zerosofadown","location":"Spain, Murcia, Lorca","language":"C#","gravatar":"https://avatars0.githubusercontent.com/u/659647?v=3&s=64","followers":1,"user_stars":"4","stars":0,"organizations":[],"contributions":3,"contributionsStreak":1,"contributionsCurrentStreak":0},{"name":"Juan Pedro Lozano","login":"yreaction","location":"Murcia (Spain)","language":"JavaScript","gravatar":"https://avatars1.githubusercontent.com/u/518910?v=3&s=64","followers":1,"user_stars":"3","stars":4,"organizations":[],"contributions":3,"contributionsStreak":1,"contributionsCurrentStreak":0},{"name":"Miguel Ángel Moreno","login":"nitrico","location":"Murcia, Spain","language":"Java","gravatar":"https://avatars3.githubusercontent.com/u/340257?v=3&s=64","followers":1,"user_stars":"233","stars":0,"organizations":[],"contributions":3,"contributionsStreak":1,"contributionsCurrentStreak":0},{"name":"Roberto Serrano","login":"bilki","location":"Murcia, Spain","language":"Scala","gravatar":"https://avatars0.githubusercontent.com/u/1669748?v=3&s=64","followers":2,"user_stars":"3","stars":0,"organizations":[],"contributions":3,"contributionsStreak":1,"contributionsCurrentStreak":0},{"name":"Darkkz","login":"Darkkz","location":"Murcia","language":"","gravatar":"https://avatars2.githubusercontent.com/u/494123?v=3&s=64","followers":1,"user_stars":"16","stars":0,"organizations":[],"contributions":2,"contributionsStreak":1,"contributionsCurrentStreak":0},{"name":"Nacho","login":"coloratto","location":"Lorca (Murcia)","language":"JavaScript","gravatar":"https://avatars0.githubusercontent.com/u/490889?v=3&s=64","followers":0,"user_stars":"1","stars":1,"organizations":[],"contributions":2,"contributionsStreak":1,"contributionsCurrentStreak":0},{"name":"Juan A. Sánchez","login":"drlaguna","location":"Murcia - Spain","language":"","gravatar":"https://avatars2.githubusercontent.com/u/7996494?v=3&s=64","followers":1,"user_stars":"0","stars":0,"organizations":[],"contributions":2,"contributionsStreak":1,"contributionsCurrentStreak":0},{"name":"Santiago Aledo","login":"SoullessOne","location":"Murcia","language":"CSS","gravatar":"https://avatars3.githubusercontent.com/u/5612395?v=3&s=64","followers":4,"user_stars":"1","stars":0,"organizations":[],"contributions":2,"contributionsStreak":1,"contributionsCurrentStreak":0},{"name":"Iván","login":"ivanmoreno","location":"Murcia, Spain","language":"PHP and Python","gravatar":"https://avatars2.githubusercontent.com/u/5198677?v=3&s=64","followers":4,"user_stars":"3","stars":0,"organizations":[],"contributions":2,"contributionsStreak":1,"contributionsCurrentStreak":0},{"name":"Dionisio","login":"DionisioFG","location":"Murcia","language":"PHP","gravatar":"https://avatars0.githubusercontent.com/u/5276985?v=3&s=64","followers":0,"user_stars":"0","stars":0,"organizations":[],"contributions":2,"contributionsStreak":1,"contributionsCurrentStreak":0},{"name":"Cristian Sánchez Ruiz","login":"christiansr85","location":"Murcia, Spain","language":"","gravatar":"https://avatars0.githubusercontent.com/u/5030291?v=3&s=64","followers":0,"user_stars":"0","stars":0,"organizations":[],"contributions":2,"contributionsStreak":1,"contributionsCurrentStreak":0},{"name":"Francisco Campillo Asensio","login":"campill0","location":"Murcia","language":"CSS","gravatar":"https://avatars1.githubusercontent.com/u/3453549?v=3&s=64","followers":0,"user_stars":"0","stars":0,"organizations":[],"contributions":2,"contributionsStreak":1,"contributionsCurrentStreak":0},{"name":"Emilio López Arias","login":"SoyUnEmilio","location":"Murcia, Región de Murcia, España","language":"C#","gravatar":"https://avatars2.githubusercontent.com/u/1872807?v=3&s=64","followers":0,"user_stars":"1","stars":0,"organizations":[],"contributions":2,"contributionsStreak":1,"contributionsCurrentStreak":0},{"name":"Francisco García","login":"FGarciaLopez","location":"Murcia, Spain","language":"JavaScript","gravatar":"https://avatars2.githubusercontent.com/u/6230439?v=3&s=64","followers":0,"user_stars":"4","stars":0,"organizations":[],"contributions":1,"contributionsStreak":1,"contributionsCurrentStreak":0},{"name":"Pablo Martínez García","login":"PabloMG","location":"Murcia (Spain)","language":"","gravatar":"https://avatars3.githubusercontent.com/u/9134245?v=3&s=64","followers":0,"user_stars":"0","stars":0,"organizations":[],"contributions":1,"contributionsStreak":1,"contributionsCurrentStreak":0},{"name":"José Manuel Lucas","login":"jmlweb","location":"Murcia","language":"JavaScript","gravatar":"https://avatars3.githubusercontent.com/u/66399?v=3&s=64","followers":12,"user_stars":"27","stars":6,"organizations":[],"contributions":1,"contributionsStreak":1,"contributionsCurrentStreak":0},{"name":"Pedro Luis López","login":"pedroluislopez","location":"Murcia","language":"Python","gravatar":"https://avatars3.githubusercontent.com/u/9784609?v=3&s=64","followers":0,"user_stars":"0","stars":0,"organizations":[],"contributions":1,"contributionsStreak":1,"contributionsCurrentStreak":0},{"name":"Aruna Kulatunga","login":"arunakulat","location":"Cartagena, Murcia","language":"JavaScript","gravatar":"https://avatars0.githubusercontent.com/u/160489?v=3&s=64","followers":0,"user_stars":"12","stars":5,"organizations":["Comunicamos"],"contributions":1,"contributionsStreak":1,"contributionsCurrentStreak":0},{"name":"Daniel Portillo","login":"Habitatea","location":"Murcia","language":"","gravatar":"https://avatars3.githubusercontent.com/u/3514421?v=3&s=64","followers":0,"user_stars":"2","stars":0,"organizations":[],"contributions":1,"contributionsStreak":1,"contributionsCurrentStreak":0},{"name":"Pablo Sempere","login":"PabloClon","location":"Murcia, Spain.","language":"","gravatar":"https://avatars2.githubusercontent.com/u/1783452?v=3&s=64","followers":0,"user_stars":"1","stars":0,"organizations":[],"contributions":1,"contributionsStreak":1,"contributionsCurrentStreak":0},{"name":"Carlos Juan Gómez Peñalver","login":"carlosjgp","location":"Murcia","language":"PHP","gravatar":"https://avatars2.githubusercontent.com/u/1277613?v=3&s=64","followers":3,"user_stars":"4","stars":0,"organizations":["SuperTeam","SuperJB-Devices"],"contributions":1,"contributionsStreak":1,"contributionsCurrentStreak":0},{"name":"Jose Francisco Rives","login":"sevir","location":"Murcia, Spain","language":"JavaScript","gravatar":"https://avatars1.githubusercontent.com/u/551046?v=3&s=64","followers":6,"user_stars":"28","stars":30,"organizations":[],"contributions":1,"contributionsStreak":1,"contributionsCurrentStreak":0},{"name":"Juan Carlos Ruiz","login":"klaufel","location":"Murcia (Spain)","language":"CSS","gravatar":"https://avatars1.githubusercontent.com/u/1427623?v=3&s=64","followers":1,"user_stars":"0","stars":1,"organizations":[],"contributions":1,"contributionsStreak":1,"contributionsCurrentStreak":0}]