[{"name":"Cristian Álvarez Belaustegui","login":"belaustegui","location":"Asturias, Spain","language":"CSS","gravatar":"https://avatars2.githubusercontent.com/u/2965623?v=3&s=400","followers":5,"organizations":["weso"],"contributions":1862,"contributionsStreak":20,"contributionsCurrentStreak":0},{"name":"Jose Emilio Labra Gayo","login":"labra","location":"Asturias","language":"Scala","gravatar":"https://avatars1.githubusercontent.com/u/308369?v=3&s=400","followers":29,"organizations":["weso"],"contributions":631,"contributionsStreak":13,"contributionsCurrentStreak":0},{"name":"Ricardo García","login":"bigardone","location":"Asturias, Spain","language":"CSS","gravatar":"https://avatars2.githubusercontent.com/u/1090272?v=3&s=400","followers":7,"organizations":[],"contributions":198,"contributionsStreak":4,"contributionsCurrentStreak":0},{"name":"Tunelko","login":"tunelko","location":"Asturias","language":"JavaScript","gravatar":"https://avatars1.githubusercontent.com/u/1008217?v=3&s=400","followers":7,"organizations":["AdaFormacion"],"contributions":197,"contributionsStreak":7,"contributionsCurrentStreak":0},{"name":"Patri","login":"PatriRor","location":"Asturias","language":"Ruby","gravatar":"https://avatars0.githubusercontent.com/u/5472707?v=3&s=400","followers":5,"organizations":[],"contributions":148,"contributionsStreak":5,"contributionsCurrentStreak":0},{"name":"Álvaro Fernández González","login":"varomorf","location":"Gijón, Asturias, Spain","language":"Groovy and Java","gravatar":"https://avatars2.githubusercontent.com/u/3148090?v=3&s=400","followers":3,"organizations":[],"contributions":102,"contributionsStreak":5,"contributionsCurrentStreak":0},{"name":"Juanjo","login":"juanjofg","location":"Asturias","language":"JavaScript and CSS","gravatar":"https://avatars2.githubusercontent.com/u/883402?v=3&s=400","followers":1,"organizations":[],"contributions":98,"contributionsStreak":4,"contributionsCurrentStreak":0},{"name":"Miguel Angel Salinas Gancedo","login":"masalinas","location":"Gijón, Asturias (Spain)","language":"Java","gravatar":"https://avatars2.githubusercontent.com/u/1216181?v=3&s=400","followers":1,"organizations":[],"contributions":66,"contributionsStreak":5,"contributionsCurrentStreak":0},{"name":"Jose Enrique Álvarez","login":"joserendal","location":"Asturias, España","language":"Java","gravatar":"https://avatars2.githubusercontent.com/u/6493934?v=3&s=400","followers":3,"organizations":[],"contributions":65,"contributionsStreak":4,"contributionsCurrentStreak":0},{"name":"Pablo Escalada","login":"diesire","location":"Asturias, Spain","language":"JavaScript","gravatar":"https://avatars1.githubusercontent.com/u/1185591?v=3&s=400","followers":2,"organizations":[],"contributions":58,"contributionsStreak":4,"contributionsCurrentStreak":0},{"name":"César Luis Alvargonzález","login":"Cesarla","location":"Oviedo, Asturias, Spain","language":"Java","gravatar":"https://avatars1.githubusercontent.com/u/1880223?v=3&s=400","followers":6,"organizations":["weso"],"contributions":36,"contributionsStreak":4,"contributionsCurrentStreak":0},{"name":"Fran","login":"Frandi1313","location":"Asturias","language":"PHP","gravatar":"https://avatars2.githubusercontent.com/u/7465735?v=3&s=400","followers":2,"organizations":[],"contributions":33,"contributionsStreak":4,"contributionsCurrentStreak":0},{"name":"Esteban Montes","login":"sankosk","location":"Asturias","language":"CSS","gravatar":"https://avatars2.githubusercontent.com/u/3002802?v=3&s=400","followers":2,"organizations":[],"contributions":25,"contributionsStreak":2,"contributionsCurrentStreak":0},{"name":"Noé Fernández","login":"noeFernandez","location":"Asturias, Spain","language":"Java","gravatar":"https://avatars3.githubusercontent.com/u/1713177?v=3&s=400","followers":3,"organizations":[],"contributions":21,"contributionsStreak":1,"contributionsCurrentStreak":0},{"name":"Rodrigo Alvarez","login":"rastmails","location":"Gijón, Asturias, Spain","language":"Java","gravatar":"https://avatars3.githubusercontent.com/u/3432560?v=3&s=400","followers":5,"organizations":[],"contributions":20,"contributionsStreak":2,"contributionsCurrentStreak":0},{"name":"Diego Zapico","login":"zapiko","location":"Asturias","language":"C#","gravatar":"https://avatars0.githubusercontent.com/u/994379?v=3&s=400","followers":4,"organizations":[],"contributions":18,"contributionsStreak":2,"contributionsCurrentStreak":0},{"name":"David GG","login":"davidgg","location":"Asturias, Spain","language":"JavaScript","gravatar":"https://avatars0.githubusercontent.com/u/3048392?v=3&s=400","followers":2,"organizations":[],"contributions":13,"contributionsStreak":1,"contributionsCurrentStreak":0},{"name":"Carlos Salinas Gancedo","login":"carlos-salinas","location":"Gijon, Asturias. SPAIN","language":"Java","gravatar":"https://avatars3.githubusercontent.com/u/1190763?v=3&s=400","followers":2,"organizations":[],"contributions":12,"contributionsStreak":3,"contributionsCurrentStreak":0},{"name":"Ubic","login":"ubic","location":"Asturias (Spain)","language":"CSS and JavaScript","gravatar":"https://avatars3.githubusercontent.com/u/7187902?v=3&s=400","followers":1,"organizations":[],"contributions":10,"contributionsStreak":1,"contributionsCurrentStreak":0},{"name":"Pablo Rivera Conde","login":"pablorc","location":"Gijón, Asturias","language":"Ruby","gravatar":"https://avatars2.githubusercontent.com/u/139060?v=3&s=400","followers":8,"organizations":["asturiasrb","MediaSQ"],"contributions":8,"contributionsStreak":2,"contributionsCurrentStreak":0},{"name":"Oscar Cuadrado Mendez","login":"asturmaps","location":"Lugo de Llanera, Asturias. Spain","language":"CSS","gravatar":"https://avatars3.githubusercontent.com/u/4499445?v=3&s=400","followers":1,"organizations":[],"contributions":8,"contributionsStreak":2,"contributionsCurrentStreak":0},{"name":"José L. Corrales","login":"jlcorra","location":"Asturias, Spain","language":"Objective-C","gravatar":"https://avatars2.githubusercontent.com/u/5528716?v=3&s=400","followers":2,"organizations":[],"contributions":7,"contributionsStreak":1,"contributionsCurrentStreak":0},{"name":"Jorge Canteli","login":"jorcanvi","location":"Oviedo (Asturias - España)","language":"PHP","gravatar":"https://avatars1.githubusercontent.com/u/1357537?v=3&s=400","followers":1,"organizations":[],"contributions":3,"contributionsStreak":1,"contributionsCurrentStreak":0},{"name":"David García","login":"daviceitor","location":"Asturias","language":"Java","gravatar":"https://avatars1.githubusercontent.com/u/738564?v=3&s=400","followers":1,"organizations":[],"contributions":2,"contributionsStreak":1,"contributionsCurrentStreak":0},{"name":"Alejandro Julián López Rodríguez","login":"AlejandroJL","location":"Asturias (Spain)","language":"Objective-C and Ruby","gravatar":"https://avatars0.githubusercontent.com/u/14291?v=3&s=400","followers":22,"organizations":[],"contributions":2,"contributionsStreak":1,"contributionsCurrentStreak":0},{"name":"Raúl Gundín","login":"raulgundin","location":"Asturias, Spain","language":"Perl","gravatar":"https://avatars2.githubusercontent.com/u/212610?v=3&s=400","followers":2,"organizations":[],"contributions":1,"contributionsStreak":1,"contributionsCurrentStreak":0}]